[{"id":"Microsoft","companyPretty":"Microsoft","kind":"internet","score":40},{"id":"Yandex","companyPretty":"Yandex","kind":"internet","score":25},{"id":"Google","companyPretty":"Google","kind":"internet","score":20},{"id":"Twitter","companyPretty":"Twitter","kind":"internet","score":13},{"id":"Yahoo","companyPretty":"Yahoo","kind":"internet","score":13},{"id":"Alibaba","companyPretty":"Alibaba","kind":"internet","score":0},{"id":"Amazon","companyPretty":"Amazon","kind":"internet","score":0},{"id":"Apple","companyPretty":"Apple","kind":"internet","score":0},{"id":"Baidu","companyPretty":"Baidu","kind":"internet","score":0},{"id":"Meta","companyPretty":"Meta","kind":"internet","score":0},{"id":"Kakao","companyPretty":"Kakao","kind":"internet","score":0},{"id":"VK","companyPretty":"VK","kind":"internet","score":0},{"id":"Samsung","companyPretty":"Samsung","kind":"internet","score":0},{"id":"Tencent","companyPretty":"Tencent","kind":"internet","score":0}]