{"Yandex":{"Yandex Disk":[{"id":"F02c-Yandex-Yandex Disk-F02c.01","name":"F02c.01","position":1,"score":0,"value":"No Disclosure Found"},{"id":"F02c-Yandex-Yandex Disk-F02c.02","name":"F02c.02","position":2,"score":0,"value":"No Disclosure Found"},{"id":"F02c-Yandex-Yandex Disk-F02c.03","name":"F02c.03","position":3,"score":0,"value":"No Disclosure Found"},{"id":"F02c-Yandex-Yandex Disk-F02c.04","name":"F02c.04","position":4,"score":100,"value":"Yes"},{"id":"F02c-Yandex-Yandex Disk-F02c.05","name":"F02c.05","position":5,"score":"NA","value":"NA"},{"id":"F02c-Yandex-Yandex Disk-F02c.06","name":"F02c.06","position":6,"score":"NA","value":"NA"}],"Yandex Search":[{"id":"F02c-Yandex-Yandex Search-F02c.01","name":"F02c.01","position":1,"score":0,"value":"No Disclosure Found"},{"id":"F02c-Yandex-Yandex Search-F02c.02","name":"F02c.02","position":2,"score":0,"value":"No Disclosure Found"},{"id":"F02c-Yandex-Yandex Search-F02c.03","name":"F02c.03","position":3,"score":0,"value":"No Disclosure Found"},{"id":"F02c-Yandex-Yandex Search-F02c.04","name":"F02c.04","position":4,"score":100,"value":"Yes"},{"id":"F02c-Yandex-Yandex Search-F02c.05","name":"F02c.05","position":5,"score":"NA","value":"NA"},{"id":"F02c-Yandex-Yandex Search-F02c.06","name":"F02c.06","position":6,"score":"NA","value":"NA"}],"Yandex Mail":[{"id":"F02c-Yandex-Yandex Mail-F02c.01","name":"F02c.01","position":1,"score":0,"value":"No Disclosure Found"},{"id":"F02c-Yandex-Yandex Mail-F02c.02","name":"F02c.02","position":2,"score":0,"value":"No Disclosure Found"},{"id":"F02c-Yandex-Yandex Mail-F02c.03","name":"F02c.03","position":3,"score":0,"value":"No Disclosure Found"},{"id":"F02c-Yandex-Yandex Mail-F02c.04","name":"F02c.04","position":4,"score":100,"value":"Yes"},{"id":"F02c-Yandex-Yandex Mail-F02c.05","name":"F02c.05","position":5,"score":"NA","value":"NA"},{"id":"F02c-Yandex-Yandex Mail-F02c.06","name":"F02c.06","position":6,"score":"NA","value":"NA"}]},"Vodafone":{"Fixed-line broadband":[{"id":"F02c-Vodafone-Fixed-line broadband-F02c.01","name":"F02c.01","position":1,"score":0,"value":"No Disclosure Found"},{"id":"F02c-Vodafone-Fixed-line broadband-F02c.02","name":"F02c.02","position":2,"score":0,"value":"No Disclosure Found"},{"id":"F02c-Vodafone-Fixed-line broadband-F02c.03","name":"F02c.03","position":3,"score":0,"value":"No Disclosure Found"},{"id":"F02c-Vodafone-Fixed-line broadband-F02c.04","name":"F02c.04","position":4,"score":0,"value":"No Disclosure Found"},{"id":"F02c-Vodafone-Fixed-line broadband-F02c.05","name":"F02c.05","position":5,"score":"NA","value":"NA"},{"id":"F02c-Vodafone-Fixed-line broadband-F02c.06","name":"F02c.06","position":6,"score":"NA","value":"NA"}],"Postpaid mobile":[{"id":"F02c-Vodafone-Postpaid mobile-F02c.01","name":"F02c.01","position":1,"score":0,"value":"No Disclosure Found"},{"id":"F02c-Vodafone-Postpaid mobile-F02c.02","name":"F02c.02","position":2,"score":0,"value":"No Disclosure Found"},{"id":"F02c-Vodafone-Postpaid mobile-F02c.03","name":"F02c.03","position":3,"score":0,"value":"No Disclosure Found"},{"id":"F02c-Vodafone-Postpaid mobile-F02c.04","name":"F02c.04","position":4,"score":0,"value":"No Disclosure Found"},{"id":"F02c-Vodafone-Postpaid mobile-F02c.05","name":"F02c.05","position":5,"score":"NA","value":"NA"},{"id":"F02c-Vodafone-Postpaid mobile-F02c.06","name":"F02c.06","position":6,"score":"NA","value":"NA"}],"Prepaid mobile":[{"id":"F02c-Vodafone-Prepaid mobile-F02c.01","name":"F02c.01","position":1,"score":0,"value":"No Disclosure Found"},{"id":"F02c-Vodafone-Prepaid mobile-F02c.02","name":"F02c.02","position":2,"score":0,"value":"No Disclosure Found"},{"id":"F02c-Vodafone-Prepaid mobile-F02c.03","name":"F02c.03","position":3,"score":0,"value":"No Disclosure Found"},{"id":"F02c-Vodafone-Prepaid mobile-F02c.04","name":"F02c.04","position":4,"score":0,"value":"No Disclosure Found"},{"id":"F02c-Vodafone-Prepaid mobile-F02c.05","name":"F02c.05","position":5,"score":"NA","value":"NA"},{"id":"F02c-Vodafone-Prepaid mobile-F02c.06","name":"F02c.06","position":6,"score":"NA","value":"NA"}]},"VerizonMedia":{"Yahoo Mail":[{"id":"F02c-VerizonMedia-Yahoo Mail-F02c.01","name":"F02c.01","position":1,"score":0,"value":"No Disclosure Found"},{"id":"F02c-VerizonMedia-Yahoo Mail-F02c.02","name":"F02c.02","position":2,"score":0,"value":"No Disclosure Found"},{"id":"F02c-VerizonMedia-Yahoo Mail-F02c.03","name":"F02c.03","position":3,"score":0,"value":"No Disclosure Found"},{"id":"F02c-VerizonMedia-Yahoo Mail-F02c.04","name":"F02c.04","position":4,"score":50,"value":"Partial"},{"id":"F02c-VerizonMedia-Yahoo Mail-F02c.05","name":"F02c.05","position":5,"score":"NA","value":"NA"},{"id":"F02c-VerizonMedia-Yahoo Mail-F02c.06","name":"F02c.06","position":6,"score":"NA","value":"NA"}]},"Twitter":{"Twitter":[{"id":"F02c-Twitter-Twitter-F02c.01","name":"F02c.01","position":1,"score":0,"value":"No Disclosure Found"},{"id":"F02c-Twitter-Twitter-F02c.02","name":"F02c.02","position":2,"score":0,"value":"No Disclosure Found"},{"id":"F02c-Twitter-Twitter-F02c.03","name":"F02c.03","position":3,"score":0,"value":"No Disclosure Found"},{"id":"F02c-Twitter-Twitter-F02c.04","name":"F02c.04","position":4,"score":50,"value":"Partial"},{"id":"F02c-Twitter-Twitter-F02c.05","name":"F02c.05","position":5,"score":"NA","value":"NA"},{"id":"F02c-Twitter-Twitter-F02c.06","name":"F02c.06","position":6,"score":"NA","value":"NA"}]},"Tencent":{"Tencent Cloud":[{"id":"F02c-Tencent-Tencent Cloud-F02c.01","name":"F02c.01","position":1,"score":0,"value":"No Disclosure Found"},{"id":"F02c-Tencent-Tencent Cloud-F02c.02","name":"F02c.02","position":2,"score":0,"value":"No Disclosure Found"},{"id":"F02c-Tencent-Tencent Cloud-F02c.03","name":"F02c.03","position":3,"score":0,"value":"No Disclosure Found"},{"id":"F02c-Tencent-Tencent Cloud-F02c.04","name":"F02c.04","position":4,"score":0,"value":"No Disclosure Found"},{"id":"F02c-Tencent-Tencent Cloud-F02c.05","name":"F02c.05","position":5,"score":"NA","value":"NA"},{"id":"F02c-Tencent-Tencent Cloud-F02c.06","name":"F02c.06","position":6,"score":"NA","value":"NA"}],"WeChat":[{"id":"F02c-Tencent-WeChat-F02c.01","name":"F02c.01","position":1,"score":0,"value":"No Disclosure Found"},{"id":"F02c-Tencent-WeChat-F02c.02","name":"F02c.02","position":2,"score":0,"value":"No Disclosure Found"},{"id":"F02c-Tencent-WeChat-F02c.03","name":"F02c.03","position":3,"score":0,"value":"No Disclosure Found"},{"id":"F02c-Tencent-WeChat-F02c.04","name":"F02c.04","position":4,"score":0,"value":"No Disclosure Found"},{"id":"F02c-Tencent-WeChat-F02c.05","name":"F02c.05","position":5,"score":"NA","value":"NA"},{"id":"F02c-Tencent-WeChat-F02c.06","name":"F02c.06","position":6,"score":"NA","value":"NA"}],"QQ":[{"id":"F02c-Tencent-QQ-F02c.01","name":"F02c.01","position":1,"score":0,"value":"No Disclosure Found"},{"id":"F02c-Tencent-QQ-F02c.02","name":"F02c.02","position":2,"score":0,"value":"No Disclosure Found"},{"id":"F02c-Tencent-QQ-F02c.03","name":"F02c.03","position":3,"score":0,"value":"No Disclosure Found"},{"id":"F02c-Tencent-QQ-F02c.04","name":"F02c.04","position":4,"score":0,"value":"No Disclosure Found"},{"id":"F02c-Tencent-QQ-F02c.05","name":"F02c.05","position":5,"score":"NA","value":"NA"},{"id":"F02c-Tencent-QQ-F02c.06","name":"F02c.06","position":6,"score":"NA","value":"NA"}],"QZone":[{"id":"F02c-Tencent-QZone-F02c.01","name":"F02c.01","position":1,"score":0,"value":"No Disclosure Found"},{"id":"F02c-Tencent-QZone-F02c.02","name":"F02c.02","position":2,"score":0,"value":"No Disclosure Found"},{"id":"F02c-Tencent-QZone-F02c.03","name":"F02c.03","position":3,"score":0,"value":"No Disclosure Found"},{"id":"F02c-Tencent-QZone-F02c.04","name":"F02c.04","position":4,"score":0,"value":"No Disclosure Found"},{"id":"F02c-Tencent-QZone-F02c.05","name":"F02c.05","position":5,"score":"NA","value":"NA"},{"id":"F02c-Tencent-QZone-F02c.06","name":"F02c.06","position":6,"score":"NA","value":"NA"}]},"Telenor":{"Fixed-line broadband":[{"id":"F02c-Telenor-Fixed-line broadband-F02c.01","name":"F02c.01","position":1,"score":50,"value":"Partial"},{"id":"F02c-Telenor-Fixed-line broadband-F02c.02","name":"F02c.02","position":2,"score":0,"value":"No Disclosure Found"},{"id":"F02c-Telenor-Fixed-line broadband-F02c.03","name":"F02c.03","position":3,"score":50,"value":"Partial"},{"id":"F02c-Telenor-Fixed-line broadband-F02c.04","name":"F02c.04","position":4,"score":0,"value":"No Disclosure Found"},{"id":"F02c-Telenor-Fixed-line broadband-F02c.05","name":"F02c.05","position":5,"score":"NA","value":"NA"},{"id":"F02c-Telenor-Fixed-line broadband-F02c.06","name":"F02c.06","position":6,"score":"NA","value":"NA"}],"Postpaid mobile":[{"id":"F02c-Telenor-Postpaid mobile-F02c.01","name":"F02c.01","position":1,"score":50,"value":"Partial"},{"id":"F02c-Telenor-Postpaid mobile-F02c.02","name":"F02c.02","position":2,"score":0,"value":"No Disclosure Found"},{"id":"F02c-Telenor-Postpaid mobile-F02c.03","name":"F02c.03","position":3,"score":50,"value":"Partial"},{"id":"F02c-Telenor-Postpaid mobile-F02c.04","name":"F02c.04","position":4,"score":0,"value":"No Disclosure Found"},{"id":"F02c-Telenor-Postpaid mobile-F02c.05","name":"F02c.05","position":5,"score":"NA","value":"NA"},{"id":"F02c-Telenor-Postpaid mobile-F02c.06","name":"F02c.06","position":6,"score":"NA","value":"NA"}],"Prepaid mobile":[{"id":"F02c-Telenor-Prepaid mobile-F02c.01","name":"F02c.01","position":1,"score":50,"value":"Partial"},{"id":"F02c-Telenor-Prepaid mobile-F02c.02","name":"F02c.02","position":2,"score":0,"value":"No Disclosure Found"},{"id":"F02c-Telenor-Prepaid mobile-F02c.03","name":"F02c.03","position":3,"score":50,"value":"Partial"},{"id":"F02c-Telenor-Prepaid mobile-F02c.04","name":"F02c.04","position":4,"score":0,"value":"No Disclosure Found"},{"id":"F02c-Telenor-Prepaid mobile-F02c.05","name":"F02c.05","position":5,"score":"NA","value":"NA"},{"id":"F02c-Telenor-Prepaid mobile-F02c.06","name":"F02c.06","position":6,"score":"NA","value":"NA"}]},"Telefonica":{"Fixed-line broadband":[{"id":"F02c-Telefonica-Fixed-line broadband-F02c.01","name":"F02c.01","position":1,"score":0,"value":"No Disclosure Found"},{"id":"F02c-Telefonica-Fixed-line broadband-F02c.02","name":"F02c.02","position":2,"score":0,"value":"No Disclosure Found"},{"id":"F02c-Telefonica-Fixed-line broadband-F02c.03","name":"F02c.03","position":3,"score":0,"value":"No Disclosure Found"},{"id":"F02c-Telefonica-Fixed-line broadband-F02c.04","name":"F02c.04","position":4,"score":0,"value":"No Disclosure Found"},{"id":"F02c-Telefonica-Fixed-line broadband-F02c.05","name":"F02c.05","position":5,"score":"NA","value":"NA"},{"id":"F02c-Telefonica-Fixed-line broadband-F02c.06","name":"F02c.06","position":6,"score":"NA","value":"NA"}],"Postpaid mobile":[{"id":"F02c-Telefonica-Postpaid mobile-F02c.01","name":"F02c.01","position":1,"score":0,"value":"No Disclosure Found"},{"id":"F02c-Telefonica-Postpaid mobile-F02c.02","name":"F02c.02","position":2,"score":0,"value":"No Disclosure Found"},{"id":"F02c-Telefonica-Postpaid mobile-F02c.03","name":"F02c.03","position":3,"score":0,"value":"No Disclosure Found"},{"id":"F02c-Telefonica-Postpaid mobile-F02c.04","name":"F02c.04","position":4,"score":0,"value":"No Disclosure Found"},{"id":"F02c-Telefonica-Postpaid mobile-F02c.05","name":"F02c.05","position":5,"score":"NA","value":"NA"},{"id":"F02c-Telefonica-Postpaid mobile-F02c.06","name":"F02c.06","position":6,"score":"NA","value":"NA"}],"Prepaid mobile":[{"id":"F02c-Telefonica-Prepaid mobile-F02c.01","name":"F02c.01","position":1,"score":0,"value":"No Disclosure Found"},{"id":"F02c-Telefonica-Prepaid mobile-F02c.02","name":"F02c.02","position":2,"score":0,"value":"No Disclosure Found"},{"id":"F02c-Telefonica-Prepaid mobile-F02c.03","name":"F02c.03","position":3,"score":0,"value":"No Disclosure Found"},{"id":"F02c-Telefonica-Prepaid mobile-F02c.04","name":"F02c.04","position":4,"score":0,"value":"No Disclosure Found"},{"id":"F02c-Telefonica-Prepaid mobile-F02c.05","name":"F02c.05","position":5,"score":"NA","value":"NA"},{"id":"F02c-Telefonica-Prepaid mobile-F02c.06","name":"F02c.06","position":6,"score":"NA","value":"NA"}]},"Samsung":{"Samsung Cloud":[{"id":"F02c-Samsung-Samsung Cloud-F02c.01","name":"F02c.01","position":1,"score":0,"value":"No Disclosure Found"},{"id":"F02c-Samsung-Samsung Cloud-F02c.02","name":"F02c.02","position":2,"score":0,"value":"No Disclosure Found"},{"id":"F02c-Samsung-Samsung Cloud-F02c.03","name":"F02c.03","position":3,"score":0,"value":"No Disclosure Found"},{"id":"F02c-Samsung-Samsung Cloud-F02c.04","name":"F02c.04","position":4,"score":0,"value":"No Disclosure Found"},{"id":"F02c-Samsung-Samsung Cloud-F02c.05","name":"F02c.05","position":5,"score":"NA","value":"NA"},{"id":"F02c-Samsung-Samsung Cloud-F02c.06","name":"F02c.06","position":6,"score":"NA","value":"NA"}],"Samsung implementation of Android":[{"id":"F02c-Samsung-Samsung implementation of Android-F02c.01","name":"F02c.01","position":1,"score":0,"value":"No Disclosure Found"},{"id":"F02c-Samsung-Samsung implementation of Android-F02c.02","name":"F02c.02","position":2,"score":0,"value":"No Disclosure Found"},{"id":"F02c-Samsung-Samsung implementation of Android-F02c.03","name":"F02c.03","position":3,"score":0,"value":"No Disclosure Found"},{"id":"F02c-Samsung-Samsung implementation of Android-F02c.04","name":"F02c.04","position":4,"score":0,"value":"No Disclosure Found"},{"id":"F02c-Samsung-Samsung implementation of Android-F02c.05","name":"F02c.05","position":5,"score":0,"value":"No Disclosure Found"},{"id":"F02c-Samsung-Samsung implementation of Android-F02c.06","name":"F02c.06","position":6,"score":"NA","value":"NA"}]},"Orange":{"Fixed-line broadband":[{"id":"F02c-Orange-Fixed-line broadband-F02c.01","name":"F02c.01","position":1,"score":0,"value":"No Disclosure Found"},{"id":"F02c-Orange-Fixed-line broadband-F02c.02","name":"F02c.02","position":2,"score":0,"value":"No Disclosure Found"},{"id":"F02c-Orange-Fixed-line broadband-F02c.03","name":"F02c.03","position":3,"score":0,"value":"No Disclosure Found"},{"id":"F02c-Orange-Fixed-line broadband-F02c.04","name":"F02c.04","position":4,"score":0,"value":"No Disclosure Found"},{"id":"F02c-Orange-Fixed-line broadband-F02c.05","name":"F02c.05","position":5,"score":"NA","value":"NA"},{"id":"F02c-Orange-Fixed-line broadband-F02c.06","name":"F02c.06","position":6,"score":"NA","value":"NA"}],"Postpaid mobile":[{"id":"F02c-Orange-Postpaid mobile-F02c.01","name":"F02c.01","position":1,"score":0,"value":"No Disclosure Found"},{"id":"F02c-Orange-Postpaid mobile-F02c.02","name":"F02c.02","position":2,"score":0,"value":"No Disclosure Found"},{"id":"F02c-Orange-Postpaid mobile-F02c.03","name":"F02c.03","position":3,"score":0,"value":"No Disclosure Found"},{"id":"F02c-Orange-Postpaid mobile-F02c.04","name":"F02c.04","position":4,"score":0,"value":"No Disclosure Found"},{"id":"F02c-Orange-Postpaid mobile-F02c.05","name":"F02c.05","position":5,"score":"NA","value":"NA"},{"id":"F02c-Orange-Postpaid mobile-F02c.06","name":"F02c.06","position":6,"score":"NA","value":"NA"}],"Prepaid mobile":[{"id":"F02c-Orange-Prepaid mobile-F02c.01","name":"F02c.01","position":1,"score":0,"value":"No Disclosure Found"},{"id":"F02c-Orange-Prepaid mobile-F02c.02","name":"F02c.02","position":2,"score":0,"value":"No Disclosure Found"},{"id":"F02c-Orange-Prepaid mobile-F02c.03","name":"F02c.03","position":3,"score":0,"value":"No Disclosure Found"},{"id":"F02c-Orange-Prepaid mobile-F02c.04","name":"F02c.04","position":4,"score":0,"value":"No Disclosure Found"},{"id":"F02c-Orange-Prepaid mobile-F02c.05","name":"F02c.05","position":5,"score":"NA","value":"NA"},{"id":"F02c-Orange-Prepaid mobile-F02c.06","name":"F02c.06","position":6,"score":"NA","value":"NA"}]},"Ooredoo":{"Fixed-line broadband":[{"id":"F02c-Ooredoo-Fixed-line broadband-F02c.01","name":"F02c.01","position":1,"score":0,"value":"No Disclosure Found"},{"id":"F02c-Ooredoo-Fixed-line broadband-F02c.02","name":"F02c.02","position":2,"score":0,"value":"No Disclosure Found"},{"id":"F02c-Ooredoo-Fixed-line broadband-F02c.03","name":"F02c.03","position":3,"score":0,"value":"No Disclosure Found"},{"id":"F02c-Ooredoo-Fixed-line broadband-F02c.04","name":"F02c.04","position":4,"score":0,"value":"No Disclosure Found"},{"id":"F02c-Ooredoo-Fixed-line broadband-F02c.05","name":"F02c.05","position":5,"score":"NA","value":"NA"},{"id":"F02c-Ooredoo-Fixed-line broadband-F02c.06","name":"F02c.06","position":6,"score":"NA","value":"NA"}],"Postpaid mobile":[{"id":"F02c-Ooredoo-Postpaid mobile-F02c.01","name":"F02c.01","position":1,"score":0,"value":"No Disclosure Found"},{"id":"F02c-Ooredoo-Postpaid mobile-F02c.02","name":"F02c.02","position":2,"score":0,"value":"No Disclosure Found"},{"id":"F02c-Ooredoo-Postpaid mobile-F02c.03","name":"F02c.03","position":3,"score":0,"value":"No Disclosure Found"},{"id":"F02c-Ooredoo-Postpaid mobile-F02c.04","name":"F02c.04","position":4,"score":0,"value":"No Disclosure Found"},{"id":"F02c-Ooredoo-Postpaid mobile-F02c.05","name":"F02c.05","position":5,"score":"NA","value":"NA"},{"id":"F02c-Ooredoo-Postpaid mobile-F02c.06","name":"F02c.06","position":6,"score":"NA","value":"NA"}],"Prepaid mobile":[{"id":"F02c-Ooredoo-Prepaid mobile-F02c.01","name":"F02c.01","position":1,"score":0,"value":"No Disclosure Found"},{"id":"F02c-Ooredoo-Prepaid mobile-F02c.02","name":"F02c.02","position":2,"score":0,"value":"No Disclosure Found"},{"id":"F02c-Ooredoo-Prepaid mobile-F02c.03","name":"F02c.03","position":3,"score":0,"value":"No Disclosure Found"},{"id":"F02c-Ooredoo-Prepaid mobile-F02c.04","name":"F02c.04","position":4,"score":0,"value":"No Disclosure Found"},{"id":"F02c-Ooredoo-Prepaid mobile-F02c.05","name":"F02c.05","position":5,"score":"NA","value":"NA"},{"id":"F02c-Ooredoo-Prepaid mobile-F02c.06","name":"F02c.06","position":6,"score":"NA","value":"NA"}]},"MTN":{"Fixed-line broadband":[{"id":"F02c-MTN-Fixed-line broadband-F02c.01","name":"F02c.01","position":1,"score":0,"value":"No Disclosure Found"},{"id":"F02c-MTN-Fixed-line broadband-F02c.02","name":"F02c.02","position":2,"score":0,"value":"No Disclosure Found"},{"id":"F02c-MTN-Fixed-line broadband-F02c.03","name":"F02c.03","position":3,"score":0,"value":"No Disclosure Found"},{"id":"F02c-MTN-Fixed-line broadband-F02c.04","name":"F02c.04","position":4,"score":0,"value":"No Disclosure Found"},{"id":"F02c-MTN-Fixed-line broadband-F02c.05","name":"F02c.05","position":5,"score":"NA","value":"NA"},{"id":"F02c-MTN-Fixed-line broadband-F02c.06","name":"F02c.06","position":6,"score":"NA","value":"NA"}],"Postpaid mobile":[{"id":"F02c-MTN-Postpaid mobile-F02c.01","name":"F02c.01","position":1,"score":0,"value":"No"},{"id":"F02c-MTN-Postpaid mobile-F02c.02","name":"F02c.02","position":2,"score":0,"value":"No"},{"id":"F02c-MTN-Postpaid mobile-F02c.03","name":"F02c.03","position":3,"score":0,"value":"No"},{"id":"F02c-MTN-Postpaid mobile-F02c.04","name":"F02c.04","position":4,"score":0,"value":"No Disclosure Found"},{"id":"F02c-MTN-Postpaid mobile-F02c.05","name":"F02c.05","position":5,"score":"NA","value":"NA"},{"id":"F02c-MTN-Postpaid mobile-F02c.06","name":"F02c.06","position":6,"score":"NA","value":"NA"}],"Prepaid mobile":[{"id":"F02c-MTN-Prepaid mobile-F02c.01","name":"F02c.01","position":1,"score":0,"value":"No"},{"id":"F02c-MTN-Prepaid mobile-F02c.02","name":"F02c.02","position":2,"score":0,"value":"No"},{"id":"F02c-MTN-Prepaid mobile-F02c.03","name":"F02c.03","position":3,"score":0,"value":"No"},{"id":"F02c-MTN-Prepaid mobile-F02c.04","name":"F02c.04","position":4,"score":0,"value":"No Disclosure Found"},{"id":"F02c-MTN-Prepaid mobile-F02c.05","name":"F02c.05","position":5,"score":"NA","value":"NA"},{"id":"F02c-MTN-Prepaid mobile-F02c.06","name":"F02c.06","position":6,"score":"NA","value":"NA"}]},"Microsoft":{"OneDrive":[{"id":"F02c-Microsoft-OneDrive-F02c.01","name":"F02c.01","position":1,"score":50,"value":"Partial"},{"id":"F02c-Microsoft-OneDrive-F02c.02","name":"F02c.02","position":2,"score":50,"value":"Partial"},{"id":"F02c-Microsoft-OneDrive-F02c.03","name":"F02c.03","position":3,"score":0,"value":"No"},{"id":"F02c-Microsoft-OneDrive-F02c.04","name":"F02c.04","position":4,"score":100,"value":"Yes"},{"id":"F02c-Microsoft-OneDrive-F02c.05","name":"F02c.05","position":5,"score":"NA","value":"NA"},{"id":"F02c-Microsoft-OneDrive-F02c.06","name":"F02c.06","position":6,"score":"NA","value":"NA"}],"Skype":[{"id":"F02c-Microsoft-Skype-F02c.01","name":"F02c.01","position":1,"score":50,"value":"Partial"},{"id":"F02c-Microsoft-Skype-F02c.02","name":"F02c.02","position":2,"score":50,"value":"Partial"},{"id":"F02c-Microsoft-Skype-F02c.03","name":"F02c.03","position":3,"score":0,"value":"No"},{"id":"F02c-Microsoft-Skype-F02c.04","name":"F02c.04","position":4,"score":100,"value":"Yes"},{"id":"F02c-Microsoft-Skype-F02c.05","name":"F02c.05","position":5,"score":"NA","value":"NA"},{"id":"F02c-Microsoft-Skype-F02c.06","name":"F02c.06","position":6,"score":"NA","value":"NA"}],"Outlook.com":[{"id":"F02c-Microsoft-Outlook.com-F02c.01","name":"F02c.01","position":1,"score":50,"value":"Partial"},{"id":"F02c-Microsoft-Outlook.com-F02c.02","name":"F02c.02","position":2,"score":50,"value":"Partial"},{"id":"F02c-Microsoft-Outlook.com-F02c.03","name":"F02c.03","position":3,"score":0,"value":"No"},{"id":"F02c-Microsoft-Outlook.com-F02c.04","name":"F02c.04","position":4,"score":100,"value":"Yes"},{"id":"F02c-Microsoft-Outlook.com-F02c.05","name":"F02c.05","position":5,"score":"NA","value":"NA"},{"id":"F02c-Microsoft-Outlook.com-F02c.06","name":"F02c.06","position":6,"score":"NA","value":"NA"}],"Bing":[{"id":"F02c-Microsoft-Bing-F02c.01","name":"F02c.01","position":1,"score":50,"value":"Partial"},{"id":"F02c-Microsoft-Bing-F02c.02","name":"F02c.02","position":2,"score":50,"value":"Partial"},{"id":"F02c-Microsoft-Bing-F02c.03","name":"F02c.03","position":3,"score":0,"value":"No"},{"id":"F02c-Microsoft-Bing-F02c.04","name":"F02c.04","position":4,"score":100,"value":"Yes"},{"id":"F02c-Microsoft-Bing-F02c.05","name":"F02c.05","position":5,"score":"NA","value":"NA"},{"id":"F02c-Microsoft-Bing-F02c.06","name":"F02c.06","position":6,"score":"NA","value":"NA"}]},"MailRu":{"Mail.Ru Cloud Solutions":[{"id":"F02c-MailRu-Mail.Ru Cloud Solutions-F02c.01","name":"F02c.01","position":1,"score":0,"value":"No Disclosure Found"},{"id":"F02c-MailRu-Mail.Ru Cloud Solutions-F02c.02","name":"F02c.02","position":2,"score":0,"value":"No Disclosure Found"},{"id":"F02c-MailRu-Mail.Ru Cloud Solutions-F02c.03","name":"F02c.03","position":3,"score":0,"value":"No Disclosure Found"},{"id":"F02c-MailRu-Mail.Ru Cloud Solutions-F02c.04","name":"F02c.04","position":4,"score":0,"value":"No Disclosure Found"},{"id":"F02c-MailRu-Mail.Ru Cloud Solutions-F02c.05","name":"F02c.05","position":5,"score":"NA","value":"NA"},{"id":"F02c-MailRu-Mail.Ru Cloud Solutions-F02c.06","name":"F02c.06","position":6,"score":"NA","value":"NA"}],"Mail.Ru Agent":[{"id":"F02c-MailRu-Mail.Ru Agent-F02c.01","name":"F02c.01","position":1,"score":0,"value":"No Disclosure Found"},{"id":"F02c-MailRu-Mail.Ru Agent-F02c.02","name":"F02c.02","position":2,"score":0,"value":"No Disclosure Found"},{"id":"F02c-MailRu-Mail.Ru Agent-F02c.03","name":"F02c.03","position":3,"score":0,"value":"No Disclosure Found"},{"id":"F02c-MailRu-Mail.Ru Agent-F02c.04","name":"F02c.04","position":4,"score":0,"value":"No Disclosure Found"},{"id":"F02c-MailRu-Mail.Ru Agent-F02c.05","name":"F02c.05","position":5,"score":"NA","value":"NA"},{"id":"F02c-MailRu-Mail.Ru Agent-F02c.06","name":"F02c.06","position":6,"score":"NA","value":"NA"}],"Mail.Ru email":[{"id":"F02c-MailRu-Mail.Ru email-F02c.01","name":"F02c.01","position":1,"score":0,"value":"No Disclosure Found"},{"id":"F02c-MailRu-Mail.Ru email-F02c.02","name":"F02c.02","position":2,"score":0,"value":"No Disclosure Found"},{"id":"F02c-MailRu-Mail.Ru email-F02c.03","name":"F02c.03","position":3,"score":0,"value":"No Disclosure Found"},{"id":"F02c-MailRu-Mail.Ru email-F02c.04","name":"F02c.04","position":4,"score":0,"value":"No Disclosure Found"},{"id":"F02c-MailRu-Mail.Ru email-F02c.05","name":"F02c.05","position":5,"score":"NA","value":"NA"},{"id":"F02c-MailRu-Mail.Ru email-F02c.06","name":"F02c.06","position":6,"score":"NA","value":"NA"}],"VKontakte":[{"id":"F02c-MailRu-VKontakte-F02c.01","name":"F02c.01","position":1,"score":0,"value":"No Disclosure Found"},{"id":"F02c-MailRu-VKontakte-F02c.02","name":"F02c.02","position":2,"score":0,"value":"No Disclosure Found"},{"id":"F02c-MailRu-VKontakte-F02c.03","name":"F02c.03","position":3,"score":0,"value":"No Disclosure Found"},{"id":"F02c-MailRu-VKontakte-F02c.04","name":"F02c.04","position":4,"score":0,"value":"No Disclosure Found"},{"id":"F02c-MailRu-VKontakte-F02c.05","name":"F02c.05","position":5,"score":"NA","value":"NA"},{"id":"F02c-MailRu-VKontakte-F02c.06","name":"F02c.06","position":6,"score":"NA","value":"NA"}]},"Kakao":{"KakaoTalk":[{"id":"F02c-Kakao-KakaoTalk-F02c.01","name":"F02c.01","position":1,"score":0,"value":"No Disclosure Found"},{"id":"F02c-Kakao-KakaoTalk-F02c.02","name":"F02c.02","position":2,"score":0,"value":"No Disclosure Found"},{"id":"F02c-Kakao-KakaoTalk-F02c.03","name":"F02c.03","position":3,"score":0,"value":"No Disclosure Found"},{"id":"F02c-Kakao-KakaoTalk-F02c.04","name":"F02c.04","position":4,"score":0,"value":"No Disclosure Found"},{"id":"F02c-Kakao-KakaoTalk-F02c.05","name":"F02c.05","position":5,"score":"NA","value":"NA"},{"id":"F02c-Kakao-KakaoTalk-F02c.06","name":"F02c.06","position":6,"score":"NA","value":"NA"}],"Daum Mail":[{"id":"F02c-Kakao-Daum Mail-F02c.01","name":"F02c.01","position":1,"score":0,"value":"No Disclosure Found"},{"id":"F02c-Kakao-Daum Mail-F02c.02","name":"F02c.02","position":2,"score":0,"value":"No Disclosure Found"},{"id":"F02c-Kakao-Daum Mail-F02c.03","name":"F02c.03","position":3,"score":0,"value":"No Disclosure Found"},{"id":"F02c-Kakao-Daum Mail-F02c.04","name":"F02c.04","position":4,"score":0,"value":"No Disclosure Found"},{"id":"F02c-Kakao-Daum Mail-F02c.05","name":"F02c.05","position":5,"score":"NA","value":"NA"},{"id":"F02c-Kakao-Daum Mail-F02c.06","name":"F02c.06","position":6,"score":"NA","value":"NA"}],"Daum Search":[{"id":"F02c-Kakao-Daum Search-F02c.01","name":"F02c.01","position":1,"score":0,"value":"No Disclosure Found"},{"id":"F02c-Kakao-Daum Search-F02c.02","name":"F02c.02","position":2,"score":0,"value":"No Disclosure Found"},{"id":"F02c-Kakao-Daum Search-F02c.03","name":"F02c.03","position":3,"score":0,"value":"No Disclosure Found"},{"id":"F02c-Kakao-Daum Search-F02c.04","name":"F02c.04","position":4,"score":0,"value":"No Disclosure Found"},{"id":"F02c-Kakao-Daum Search-F02c.05","name":"F02c.05","position":5,"score":"NA","value":"NA"},{"id":"F02c-Kakao-Daum Search-F02c.06","name":"F02c.06","position":6,"score":"NA","value":"NA"}]},"Google":{"Google Drive":[{"id":"F02c-Google-Google Drive-F02c.01","name":"F02c.01","position":1,"score":0,"value":"No Disclosure Found"},{"id":"F02c-Google-Google Drive-F02c.02","name":"F02c.02","position":2,"score":0,"value":"No Disclosure Found"},{"id":"F02c-Google-Google Drive-F02c.03","name":"F02c.03","position":3,"score":0,"value":"No Disclosure Found"},{"id":"F02c-Google-Google Drive-F02c.04","name":"F02c.04","position":4,"score":100,"value":"Yes"},{"id":"F02c-Google-Google Drive-F02c.05","name":"F02c.05","position":5,"score":"NA","value":"NA"},{"id":"F02c-Google-Google Drive-F02c.06","name":"F02c.06","position":6,"score":"NA","value":"NA"}],"Android mobile ecosystem":[{"id":"F02c-Google-Android mobile ecosystem-F02c.01","name":"F02c.01","position":1,"score":0,"value":"No Disclosure Found"},{"id":"F02c-Google-Android mobile ecosystem-F02c.02","name":"F02c.02","position":2,"score":0,"value":"No Disclosure Found"},{"id":"F02c-Google-Android mobile ecosystem-F02c.03","name":"F02c.03","position":3,"score":0,"value":"No Disclosure Found"},{"id":"F02c-Google-Android mobile ecosystem-F02c.04","name":"F02c.04","position":4,"score":100,"value":"Yes"},{"id":"F02c-Google-Android mobile ecosystem-F02c.05","name":"F02c.05","position":5,"score":0,"value":"No Disclosure Found"},{"id":"F02c-Google-Android mobile ecosystem-F02c.06","name":"F02c.06","position":6,"score":"NA","value":"NA"}],"YouTube":[{"id":"F02c-Google-YouTube-F02c.01","name":"F02c.01","position":1,"score":0,"value":"No Disclosure Found"},{"id":"F02c-Google-YouTube-F02c.02","name":"F02c.02","position":2,"score":0,"value":"No Disclosure Found"},{"id":"F02c-Google-YouTube-F02c.03","name":"F02c.03","position":3,"score":0,"value":"No Disclosure Found"},{"id":"F02c-Google-YouTube-F02c.04","name":"F02c.04","position":4,"score":100,"value":"Yes"},{"id":"F02c-Google-YouTube-F02c.05","name":"F02c.05","position":5,"score":"NA","value":"NA"},{"id":"F02c-Google-YouTube-F02c.06","name":"F02c.06","position":6,"score":"NA","value":"NA"}],"Gmail":[{"id":"F02c-Google-Gmail-F02c.01","name":"F02c.01","position":1,"score":0,"value":"No Disclosure Found"},{"id":"F02c-Google-Gmail-F02c.02","name":"F02c.02","position":2,"score":0,"value":"No Disclosure Found"},{"id":"F02c-Google-Gmail-F02c.03","name":"F02c.03","position":3,"score":0,"value":"No Disclosure Found"},{"id":"F02c-Google-Gmail-F02c.04","name":"F02c.04","position":4,"score":100,"value":"Yes"},{"id":"F02c-Google-Gmail-F02c.05","name":"F02c.05","position":5,"score":"NA","value":"NA"},{"id":"F02c-Google-Gmail-F02c.06","name":"F02c.06","position":6,"score":"NA","value":"NA"}],"Google Search":[{"id":"F02c-Google-Google Search-F02c.01","name":"F02c.01","position":1,"score":0,"value":"No Disclosure Found"},{"id":"F02c-Google-Google Search-F02c.02","name":"F02c.02","position":2,"score":0,"value":"No Disclosure Found"},{"id":"F02c-Google-Google Search-F02c.03","name":"F02c.03","position":3,"score":0,"value":"No Disclosure Found"},{"id":"F02c-Google-Google Search-F02c.04","name":"F02c.04","position":4,"score":100,"value":"Yes"},{"id":"F02c-Google-Google Search-F02c.05","name":"F02c.05","position":5,"score":"NA","value":"NA"},{"id":"F02c-Google-Google Search-F02c.06","name":"F02c.06","position":6,"score":"NA","value":"NA"}]},"Facebook":{"Messenger":[{"id":"F02c-Facebook-Messenger-F02c.01","name":"F02c.01","position":1,"score":0,"value":"No"},{"id":"F02c-Facebook-Messenger-F02c.02","name":"F02c.02","position":2,"score":0,"value":"No"},{"id":"F02c-Facebook-Messenger-F02c.03","name":"F02c.03","position":3,"score":0,"value":"No"},{"id":"F02c-Facebook-Messenger-F02c.04","name":"F02c.04","position":4,"score":0,"value":"No Disclosure Found"},{"id":"F02c-Facebook-Messenger-F02c.05","name":"F02c.05","position":5,"score":"NA","value":"NA"},{"id":"F02c-Facebook-Messenger-F02c.06","name":"F02c.06","position":6,"score":"NA","value":"NA"}],"WhatsApp":[{"id":"F02c-Facebook-WhatsApp-F02c.01","name":"F02c.01","position":1,"score":0,"value":"No"},{"id":"F02c-Facebook-WhatsApp-F02c.02","name":"F02c.02","position":2,"score":0,"value":"No"},{"id":"F02c-Facebook-WhatsApp-F02c.03","name":"F02c.03","position":3,"score":0,"value":"No"},{"id":"F02c-Facebook-WhatsApp-F02c.04","name":"F02c.04","position":4,"score":0,"value":"No Disclosure Found"},{"id":"F02c-Facebook-WhatsApp-F02c.05","name":"F02c.05","position":5,"score":"NA","value":"NA"},{"id":"F02c-Facebook-WhatsApp-F02c.06","name":"F02c.06","position":6,"score":"NA","value":"NA"}],"Instagram":[{"id":"F02c-Facebook-Instagram-F02c.01","name":"F02c.01","position":1,"score":0,"value":"No"},{"id":"F02c-Facebook-Instagram-F02c.02","name":"F02c.02","position":2,"score":0,"value":"No"},{"id":"F02c-Facebook-Instagram-F02c.03","name":"F02c.03","position":3,"score":0,"value":"No"},{"id":"F02c-Facebook-Instagram-F02c.04","name":"F02c.04","position":4,"score":0,"value":"No Disclosure Found"},{"id":"F02c-Facebook-Instagram-F02c.05","name":"F02c.05","position":5,"score":"NA","value":"NA"},{"id":"F02c-Facebook-Instagram-F02c.06","name":"F02c.06","position":6,"score":"NA","value":"NA"}],"Facebook":[{"id":"F02c-Facebook-Facebook-F02c.01","name":"F02c.01","position":1,"score":0,"value":"No"},{"id":"F02c-Facebook-Facebook-F02c.02","name":"F02c.02","position":2,"score":0,"value":"No"},{"id":"F02c-Facebook-Facebook-F02c.03","name":"F02c.03","position":3,"score":0,"value":"No"},{"id":"F02c-Facebook-Facebook-F02c.04","name":"F02c.04","position":4,"score":0,"value":"No Disclosure Found"},{"id":"F02c-Facebook-Facebook-F02c.05","name":"F02c.05","position":5,"score":"NA","value":"NA"},{"id":"F02c-Facebook-Facebook-F02c.06","name":"F02c.06","position":6,"score":"NA","value":"NA"}]},"Etisalat":{"Fixed-line broadband":[{"id":"F02c-Etisalat-Fixed-line broadband-F02c.01","name":"F02c.01","position":1,"score":0,"value":"No Disclosure Found"},{"id":"F02c-Etisalat-Fixed-line broadband-F02c.02","name":"F02c.02","position":2,"score":0,"value":"No Disclosure Found"},{"id":"F02c-Etisalat-Fixed-line broadband-F02c.03","name":"F02c.03","position":3,"score":0,"value":"No Disclosure Found"},{"id":"F02c-Etisalat-Fixed-line broadband-F02c.04","name":"F02c.04","position":4,"score":0,"value":"No Disclosure Found"},{"id":"F02c-Etisalat-Fixed-line broadband-F02c.05","name":"F02c.05","position":5,"score":"NA","value":"NA"},{"id":"F02c-Etisalat-Fixed-line broadband-F02c.06","name":"F02c.06","position":6,"score":"NA","value":"NA"}],"Postpaid mobile":[{"id":"F02c-Etisalat-Postpaid mobile-F02c.01","name":"F02c.01","position":1,"score":0,"value":"No Disclosure Found"},{"id":"F02c-Etisalat-Postpaid mobile-F02c.02","name":"F02c.02","position":2,"score":0,"value":"No Disclosure Found"},{"id":"F02c-Etisalat-Postpaid mobile-F02c.03","name":"F02c.03","position":3,"score":0,"value":"No Disclosure Found"},{"id":"F02c-Etisalat-Postpaid mobile-F02c.04","name":"F02c.04","position":4,"score":0,"value":"No Disclosure Found"},{"id":"F02c-Etisalat-Postpaid mobile-F02c.05","name":"F02c.05","position":5,"score":"NA","value":"NA"},{"id":"F02c-Etisalat-Postpaid mobile-F02c.06","name":"F02c.06","position":6,"score":"NA","value":"NA"}],"Prepaid mobile":[{"id":"F02c-Etisalat-Prepaid mobile-F02c.01","name":"F02c.01","position":1,"score":0,"value":"No Disclosure Found"},{"id":"F02c-Etisalat-Prepaid mobile-F02c.02","name":"F02c.02","position":2,"score":0,"value":"No Disclosure Found"},{"id":"F02c-Etisalat-Prepaid mobile-F02c.03","name":"F02c.03","position":3,"score":0,"value":"No Disclosure Found"},{"id":"F02c-Etisalat-Prepaid mobile-F02c.04","name":"F02c.04","position":4,"score":0,"value":"No Disclosure Found"},{"id":"F02c-Etisalat-Prepaid mobile-F02c.05","name":"F02c.05","position":5,"score":"NA","value":"NA"},{"id":"F02c-Etisalat-Prepaid mobile-F02c.06","name":"F02c.06","position":6,"score":"NA","value":"NA"}]},"DeutscheTelekom":{"Fixed-line broadband":[{"id":"F02c-DeutscheTelekom-Fixed-line broadband-F02c.01","name":"F02c.01","position":1,"score":0,"value":"No Disclosure Found"},{"id":"F02c-DeutscheTelekom-Fixed-line broadband-F02c.02","name":"F02c.02","position":2,"score":0,"value":"No Disclosure Found"},{"id":"F02c-DeutscheTelekom-Fixed-line broadband-F02c.03","name":"F02c.03","position":3,"score":0,"value":"No Disclosure Found"},{"id":"F02c-DeutscheTelekom-Fixed-line broadband-F02c.04","name":"F02c.04","position":4,"score":0,"value":"No Disclosure Found"},{"id":"F02c-DeutscheTelekom-Fixed-line broadband-F02c.05","name":"F02c.05","position":5,"score":"NA","value":"NA"},{"id":"F02c-DeutscheTelekom-Fixed-line broadband-F02c.06","name":"F02c.06","position":6,"score":"NA","value":"NA"}],"Postpaid mobile":[{"id":"F02c-DeutscheTelekom-Postpaid mobile-F02c.01","name":"F02c.01","position":1,"score":0,"value":"No Disclosure Found"},{"id":"F02c-DeutscheTelekom-Postpaid mobile-F02c.02","name":"F02c.02","position":2,"score":0,"value":"No Disclosure Found"},{"id":"F02c-DeutscheTelekom-Postpaid mobile-F02c.03","name":"F02c.03","position":3,"score":0,"value":"No Disclosure Found"},{"id":"F02c-DeutscheTelekom-Postpaid mobile-F02c.04","name":"F02c.04","position":4,"score":0,"value":"No Disclosure Found"},{"id":"F02c-DeutscheTelekom-Postpaid mobile-F02c.05","name":"F02c.05","position":5,"score":"NA","value":"NA"},{"id":"F02c-DeutscheTelekom-Postpaid mobile-F02c.06","name":"F02c.06","position":6,"score":"NA","value":"NA"}],"Prepaid mobile":[{"id":"F02c-DeutscheTelekom-Prepaid mobile-F02c.01","name":"F02c.01","position":1,"score":0,"value":"No Disclosure Found"},{"id":"F02c-DeutscheTelekom-Prepaid mobile-F02c.02","name":"F02c.02","position":2,"score":0,"value":"No Disclosure Found"},{"id":"F02c-DeutscheTelekom-Prepaid mobile-F02c.03","name":"F02c.03","position":3,"score":0,"value":"No Disclosure Found"},{"id":"F02c-DeutscheTelekom-Prepaid mobile-F02c.04","name":"F02c.04","position":4,"score":0,"value":"No Disclosure Found"},{"id":"F02c-DeutscheTelekom-Prepaid mobile-F02c.05","name":"F02c.05","position":5,"score":"NA","value":"NA"},{"id":"F02c-DeutscheTelekom-Prepaid mobile-F02c.06","name":"F02c.06","position":6,"score":"NA","value":"NA"}]},"BhartiAirtel":{"Fixed-line broadband":[{"id":"F02c-BhartiAirtel-Fixed-line broadband-F02c.01","name":"F02c.01","position":1,"score":0,"value":"No Disclosure Found"},{"id":"F02c-BhartiAirtel-Fixed-line broadband-F02c.02","name":"F02c.02","position":2,"score":0,"value":"No Disclosure Found"},{"id":"F02c-BhartiAirtel-Fixed-line broadband-F02c.03","name":"F02c.03","position":3,"score":0,"value":"No Disclosure Found"},{"id":"F02c-BhartiAirtel-Fixed-line broadband-F02c.04","name":"F02c.04","position":4,"score":0,"value":"No Disclosure Found"},{"id":"F02c-BhartiAirtel-Fixed-line broadband-F02c.05","name":"F02c.05","position":5,"score":"NA","value":"NA"},{"id":"F02c-BhartiAirtel-Fixed-line broadband-F02c.06","name":"F02c.06","position":6,"score":"NA","value":"NA"}],"Postpaid mobile":[{"id":"F02c-BhartiAirtel-Postpaid mobile-F02c.01","name":"F02c.01","position":1,"score":0,"value":"No Disclosure Found"},{"id":"F02c-BhartiAirtel-Postpaid mobile-F02c.02","name":"F02c.02","position":2,"score":0,"value":"No Disclosure Found"},{"id":"F02c-BhartiAirtel-Postpaid mobile-F02c.03","name":"F02c.03","position":3,"score":0,"value":"No Disclosure Found"},{"id":"F02c-BhartiAirtel-Postpaid mobile-F02c.04","name":"F02c.04","position":4,"score":0,"value":"No Disclosure Found"},{"id":"F02c-BhartiAirtel-Postpaid mobile-F02c.05","name":"F02c.05","position":5,"score":"NA","value":"NA"},{"id":"F02c-BhartiAirtel-Postpaid mobile-F02c.06","name":"F02c.06","position":6,"score":"NA","value":"NA"}],"Prepaid mobile":[{"id":"F02c-BhartiAirtel-Prepaid mobile-F02c.01","name":"F02c.01","position":1,"score":0,"value":"No Disclosure Found"},{"id":"F02c-BhartiAirtel-Prepaid mobile-F02c.02","name":"F02c.02","position":2,"score":0,"value":"No Disclosure Found"},{"id":"F02c-BhartiAirtel-Prepaid mobile-F02c.03","name":"F02c.03","position":3,"score":0,"value":"No Disclosure Found"},{"id":"F02c-BhartiAirtel-Prepaid mobile-F02c.04","name":"F02c.04","position":4,"score":0,"value":"No Disclosure Found"},{"id":"F02c-BhartiAirtel-Prepaid mobile-F02c.05","name":"F02c.05","position":5,"score":"NA","value":"NA"},{"id":"F02c-BhartiAirtel-Prepaid mobile-F02c.06","name":"F02c.06","position":6,"score":"NA","value":"NA"}]},"Baidu":{"Baidu PostBar":[{"id":"F02c-Baidu-Baidu PostBar-F02c.01","name":"F02c.01","position":1,"score":0,"value":"No Disclosure Found"},{"id":"F02c-Baidu-Baidu PostBar-F02c.02","name":"F02c.02","position":2,"score":0,"value":"No Disclosure Found"},{"id":"F02c-Baidu-Baidu PostBar-F02c.03","name":"F02c.03","position":3,"score":0,"value":"No Disclosure Found"},{"id":"F02c-Baidu-Baidu PostBar-F02c.04","name":"F02c.04","position":4,"score":0,"value":"No Disclosure Found"},{"id":"F02c-Baidu-Baidu PostBar-F02c.05","name":"F02c.05","position":5,"score":"NA","value":"NA"},{"id":"F02c-Baidu-Baidu PostBar-F02c.06","name":"F02c.06","position":6,"score":"NA","value":"NA"}],"Baidu Cloud":[{"id":"F02c-Baidu-Baidu Cloud-F02c.01","name":"F02c.01","position":1,"score":0,"value":"No Disclosure Found"},{"id":"F02c-Baidu-Baidu Cloud-F02c.02","name":"F02c.02","position":2,"score":0,"value":"No Disclosure Found"},{"id":"F02c-Baidu-Baidu Cloud-F02c.03","name":"F02c.03","position":3,"score":0,"value":"No Disclosure Found"},{"id":"F02c-Baidu-Baidu Cloud-F02c.04","name":"F02c.04","position":4,"score":0,"value":"No Disclosure Found"},{"id":"F02c-Baidu-Baidu Cloud-F02c.05","name":"F02c.05","position":5,"score":"NA","value":"NA"},{"id":"F02c-Baidu-Baidu Cloud-F02c.06","name":"F02c.06","position":6,"score":"NA","value":"NA"}],"Baidu Search":[{"id":"F02c-Baidu-Baidu Search-F02c.01","name":"F02c.01","position":1,"score":0,"value":"No Disclosure Found"},{"id":"F02c-Baidu-Baidu Search-F02c.02","name":"F02c.02","position":2,"score":0,"value":"No Disclosure Found"},{"id":"F02c-Baidu-Baidu Search-F02c.03","name":"F02c.03","position":3,"score":0,"value":"No Disclosure Found"},{"id":"F02c-Baidu-Baidu Search-F02c.04","name":"F02c.04","position":4,"score":0,"value":"No Disclosure Found"},{"id":"F02c-Baidu-Baidu Search-F02c.05","name":"F02c.05","position":5,"score":"NA","value":"NA"},{"id":"F02c-Baidu-Baidu Search-F02c.06","name":"F02c.06","position":6,"score":"NA","value":"NA"}]},"Axiata":{"Fixed-line broadband":[{"id":"F02c-Axiata-Fixed-line broadband-F02c.01","name":"F02c.01","position":1,"score":0,"value":"No Disclosure Found"},{"id":"F02c-Axiata-Fixed-line broadband-F02c.02","name":"F02c.02","position":2,"score":0,"value":"No Disclosure Found"},{"id":"F02c-Axiata-Fixed-line broadband-F02c.03","name":"F02c.03","position":3,"score":0,"value":"No Disclosure Found"},{"id":"F02c-Axiata-Fixed-line broadband-F02c.04","name":"F02c.04","position":4,"score":0,"value":"No Disclosure Found"},{"id":"F02c-Axiata-Fixed-line broadband-F02c.05","name":"F02c.05","position":5,"score":"NA","value":"NA"},{"id":"F02c-Axiata-Fixed-line broadband-F02c.06","name":"F02c.06","position":6,"score":"NA","value":"NA"}],"Postpaid mobile":[{"id":"F02c-Axiata-Postpaid mobile-F02c.01","name":"F02c.01","position":1,"score":0,"value":"No Disclosure Found"},{"id":"F02c-Axiata-Postpaid mobile-F02c.02","name":"F02c.02","position":2,"score":0,"value":"No Disclosure Found"},{"id":"F02c-Axiata-Postpaid mobile-F02c.03","name":"F02c.03","position":3,"score":0,"value":"No Disclosure Found"},{"id":"F02c-Axiata-Postpaid mobile-F02c.04","name":"F02c.04","position":4,"score":0,"value":"No Disclosure Found"},{"id":"F02c-Axiata-Postpaid mobile-F02c.05","name":"F02c.05","position":5,"score":"NA","value":"NA"},{"id":"F02c-Axiata-Postpaid mobile-F02c.06","name":"F02c.06","position":6,"score":"NA","value":"NA"}],"Prepaid mobile":[{"id":"F02c-Axiata-Prepaid mobile-F02c.01","name":"F02c.01","position":1,"score":0,"value":"No Disclosure Found"},{"id":"F02c-Axiata-Prepaid mobile-F02c.02","name":"F02c.02","position":2,"score":0,"value":"No Disclosure Found"},{"id":"F02c-Axiata-Prepaid mobile-F02c.03","name":"F02c.03","position":3,"score":0,"value":"No Disclosure Found"},{"id":"F02c-Axiata-Prepaid mobile-F02c.04","name":"F02c.04","position":4,"score":0,"value":"No Disclosure Found"},{"id":"F02c-Axiata-Prepaid mobile-F02c.05","name":"F02c.05","position":5,"score":"NA","value":"NA"},{"id":"F02c-Axiata-Prepaid mobile-F02c.06","name":"F02c.06","position":6,"score":"NA","value":"NA"}]},"ATT":{"Fixed-line broadband":[{"id":"F02c-ATT-Fixed-line broadband-F02c.01","name":"F02c.01","position":1,"score":50,"value":"Partial"},{"id":"F02c-ATT-Fixed-line broadband-F02c.02","name":"F02c.02","position":2,"score":50,"value":"Partial"},{"id":"F02c-ATT-Fixed-line broadband-F02c.03","name":"F02c.03","position":3,"score":0,"value":"No"},{"id":"F02c-ATT-Fixed-line broadband-F02c.04","name":"F02c.04","position":4,"score":0,"value":"No Disclosure Found"},{"id":"F02c-ATT-Fixed-line broadband-F02c.05","name":"F02c.05","position":5,"score":"NA","value":"NA"},{"id":"F02c-ATT-Fixed-line broadband-F02c.06","name":"F02c.06","position":6,"score":"NA","value":"NA"}],"Postpaid mobile":[{"id":"F02c-ATT-Postpaid mobile-F02c.01","name":"F02c.01","position":1,"score":50,"value":"Partial"},{"id":"F02c-ATT-Postpaid mobile-F02c.02","name":"F02c.02","position":2,"score":50,"value":"Partial"},{"id":"F02c-ATT-Postpaid mobile-F02c.03","name":"F02c.03","position":3,"score":0,"value":"No"},{"id":"F02c-ATT-Postpaid mobile-F02c.04","name":"F02c.04","position":4,"score":0,"value":"No Disclosure Found"},{"id":"F02c-ATT-Postpaid mobile-F02c.05","name":"F02c.05","position":5,"score":"NA","value":"NA"},{"id":"F02c-ATT-Postpaid mobile-F02c.06","name":"F02c.06","position":6,"score":"NA","value":"NA"}],"Prepaid mobile":[{"id":"F02c-ATT-Prepaid mobile-F02c.01","name":"F02c.01","position":1,"score":50,"value":"Partial"},{"id":"F02c-ATT-Prepaid mobile-F02c.02","name":"F02c.02","position":2,"score":50,"value":"Partial"},{"id":"F02c-ATT-Prepaid mobile-F02c.03","name":"F02c.03","position":3,"score":0,"value":"No"},{"id":"F02c-ATT-Prepaid mobile-F02c.04","name":"F02c.04","position":4,"score":0,"value":"No Disclosure Found"},{"id":"F02c-ATT-Prepaid mobile-F02c.05","name":"F02c.05","position":5,"score":"NA","value":"NA"},{"id":"F02c-ATT-Prepaid mobile-F02c.06","name":"F02c.06","position":6,"score":"NA","value":"NA"}]},"Apple":{"iCloud":[{"id":"F02c-Apple-iCloud-F02c.01","name":"F02c.01","position":1,"score":0,"value":"No Disclosure Found"},{"id":"F02c-Apple-iCloud-F02c.02","name":"F02c.02","position":2,"score":0,"value":"No Disclosure Found"},{"id":"F02c-Apple-iCloud-F02c.03","name":"F02c.03","position":3,"score":0,"value":"No Disclosure Found"},{"id":"F02c-Apple-iCloud-F02c.04","name":"F02c.04","position":4,"score":0,"value":"No Disclosure Found"},{"id":"F02c-Apple-iCloud-F02c.05","name":"F02c.05","position":5,"score":"NA","value":"NA"},{"id":"F02c-Apple-iCloud-F02c.06","name":"F02c.06","position":6,"score":"NA","value":"NA"}],"iMessage":[{"id":"F02c-Apple-iMessage-F02c.01","name":"F02c.01","position":1,"score":0,"value":"No Disclosure Found"},{"id":"F02c-Apple-iMessage-F02c.02","name":"F02c.02","position":2,"score":0,"value":"No Disclosure Found"},{"id":"F02c-Apple-iMessage-F02c.03","name":"F02c.03","position":3,"score":0,"value":"No Disclosure Found"},{"id":"F02c-Apple-iMessage-F02c.04","name":"F02c.04","position":4,"score":0,"value":"No Disclosure Found"},{"id":"F02c-Apple-iMessage-F02c.05","name":"F02c.05","position":5,"score":"NA","value":"NA"},{"id":"F02c-Apple-iMessage-F02c.06","name":"F02c.06","position":6,"score":"NA","value":"NA"}],"iOS (mobile ecosystem)":[{"id":"F02c-Apple-iOS (mobile ecosystem)-F02c.01","name":"F02c.01","position":1,"score":0,"value":"No Disclosure Found"},{"id":"F02c-Apple-iOS (mobile ecosystem)-F02c.02","name":"F02c.02","position":2,"score":0,"value":"No Disclosure Found"},{"id":"F02c-Apple-iOS (mobile ecosystem)-F02c.03","name":"F02c.03","position":3,"score":0,"value":"No Disclosure Found"},{"id":"F02c-Apple-iOS (mobile ecosystem)-F02c.04","name":"F02c.04","position":4,"score":0,"value":"No Disclosure Found"},{"id":"F02c-Apple-iOS (mobile ecosystem)-F02c.05","name":"F02c.05","position":5,"score":0,"value":"No Disclosure Found"},{"id":"F02c-Apple-iOS (mobile ecosystem)-F02c.06","name":"F02c.06","position":6,"score":"NA","value":"NA"}]},"AmericaMovil":{"Postpaid mobile":[{"id":"F02c-AmericaMovil-Postpaid mobile-F02c.01","name":"F02c.01","position":1,"score":0,"value":"No Disclosure Found"},{"id":"F02c-AmericaMovil-Postpaid mobile-F02c.02","name":"F02c.02","position":2,"score":0,"value":"No Disclosure Found"},{"id":"F02c-AmericaMovil-Postpaid mobile-F02c.03","name":"F02c.03","position":3,"score":0,"value":"No Disclosure Found"},{"id":"F02c-AmericaMovil-Postpaid mobile-F02c.04","name":"F02c.04","position":4,"score":0,"value":"No Disclosure Found"},{"id":"F02c-AmericaMovil-Postpaid mobile-F02c.05","name":"F02c.05","position":5,"score":"NA","value":"NA"},{"id":"F02c-AmericaMovil-Postpaid mobile-F02c.06","name":"F02c.06","position":6,"score":"NA","value":"NA"}],"Prepaid mobile":[{"id":"F02c-AmericaMovil-Prepaid mobile-F02c.01","name":"F02c.01","position":1,"score":0,"value":"No Disclosure Found"},{"id":"F02c-AmericaMovil-Prepaid mobile-F02c.02","name":"F02c.02","position":2,"score":0,"value":"No Disclosure Found"},{"id":"F02c-AmericaMovil-Prepaid mobile-F02c.03","name":"F02c.03","position":3,"score":0,"value":"No Disclosure Found"},{"id":"F02c-AmericaMovil-Prepaid mobile-F02c.04","name":"F02c.04","position":4,"score":0,"value":"No Disclosure Found"},{"id":"F02c-AmericaMovil-Prepaid mobile-F02c.05","name":"F02c.05","position":5,"score":"NA","value":"NA"},{"id":"F02c-AmericaMovil-Prepaid mobile-F02c.06","name":"F02c.06","position":6,"score":"NA","value":"NA"}]},"Amazon":{"Amazon Cloud":[{"id":"F02c-Amazon-Amazon Cloud-F02c.01","name":"F02c.01","position":1,"score":0,"value":"No Disclosure Found"},{"id":"F02c-Amazon-Amazon Cloud-F02c.02","name":"F02c.02","position":2,"score":0,"value":"No Disclosure Found"},{"id":"F02c-Amazon-Amazon Cloud-F02c.03","name":"F02c.03","position":3,"score":0,"value":"No Disclosure Found"},{"id":"F02c-Amazon-Amazon Cloud-F02c.04","name":"F02c.04","position":4,"score":0,"value":"No Disclosure Found"},{"id":"F02c-Amazon-Amazon Cloud-F02c.05","name":"F02c.05","position":5,"score":"NA","value":"NA"},{"id":"F02c-Amazon-Amazon Cloud-F02c.06","name":"F02c.06","position":6,"score":"NA","value":"NA"}],"Alexa":[{"id":"F02c-Amazon-Alexa-F02c.01","name":"F02c.01","position":1,"score":0,"value":"No Disclosure Found"},{"id":"F02c-Amazon-Alexa-F02c.02","name":"F02c.02","position":2,"score":0,"value":"No Disclosure Found"},{"id":"F02c-Amazon-Alexa-F02c.03","name":"F02c.03","position":3,"score":0,"value":"No Disclosure Found"},{"id":"F02c-Amazon-Alexa-F02c.04","name":"F02c.04","position":4,"score":0,"value":"No Disclosure Found"},{"id":"F02c-Amazon-Alexa-F02c.05","name":"F02c.05","position":5,"score":"NA","value":"NA"},{"id":"F02c-Amazon-Alexa-F02c.06","name":"F02c.06","position":6,"score":0,"value":"No Disclosure Found"}],"Amazon.com":[{"id":"F02c-Amazon-Amazon.com-F02c.01","name":"F02c.01","position":1,"score":0,"value":"No Disclosure Found"},{"id":"F02c-Amazon-Amazon.com-F02c.02","name":"F02c.02","position":2,"score":0,"value":"No Disclosure Found"},{"id":"F02c-Amazon-Amazon.com-F02c.03","name":"F02c.03","position":3,"score":0,"value":"No Disclosure Found"},{"id":"F02c-Amazon-Amazon.com-F02c.04","name":"F02c.04","position":4,"score":0,"value":"No Disclosure Found"},{"id":"F02c-Amazon-Amazon.com-F02c.05","name":"F02c.05","position":5,"score":"NA","value":"NA"},{"id":"F02c-Amazon-Amazon.com-F02c.06","name":"F02c.06","position":6,"score":"NA","value":"NA"}]},"Alibaba":{"AliGenie":[{"id":"F02c-Alibaba-AliGenie-F02c.01","name":"F02c.01","position":1,"score":0,"value":"No Disclosure Found"},{"id":"F02c-Alibaba-AliGenie-F02c.02","name":"F02c.02","position":2,"score":0,"value":"No Disclosure Found"},{"id":"F02c-Alibaba-AliGenie-F02c.03","name":"F02c.03","position":3,"score":0,"value":"No Disclosure Found"},{"id":"F02c-Alibaba-AliGenie-F02c.04","name":"F02c.04","position":4,"score":0,"value":"No Disclosure Found"},{"id":"F02c-Alibaba-AliGenie-F02c.05","name":"F02c.05","position":5,"score":"NA","value":"NA"},{"id":"F02c-Alibaba-AliGenie-F02c.06","name":"F02c.06","position":6,"score":0,"value":"No Disclosure Found"}],"Taobao.com":[{"id":"F02c-Alibaba-Taobao.com-F02c.01","name":"F02c.01","position":1,"score":0,"value":"No Disclosure Found"},{"id":"F02c-Alibaba-Taobao.com-F02c.02","name":"F02c.02","position":2,"score":0,"value":"No Disclosure Found"},{"id":"F02c-Alibaba-Taobao.com-F02c.03","name":"F02c.03","position":3,"score":0,"value":"No Disclosure Found"},{"id":"F02c-Alibaba-Taobao.com-F02c.04","name":"F02c.04","position":4,"score":0,"value":"No Disclosure Found"},{"id":"F02c-Alibaba-Taobao.com-F02c.05","name":"F02c.05","position":5,"score":"NA","value":"NA"},{"id":"F02c-Alibaba-Taobao.com-F02c.06","name":"F02c.06","position":6,"score":"NA","value":"NA"}]}}