{"Yandex":{"Yandex Disk":[{"id":"P14-Yandex-Yandex Disk-P14.01","name":"P14.01","position":1,"score":100,"value":"Yes"},{"id":"P14-Yandex-Yandex Disk-P14.02","name":"P14.02","position":2,"score":100,"value":"Yes"},{"id":"P14-Yandex-Yandex Disk-P14.03","name":"P14.03","position":3,"score":0,"value":"No Disclosure Found"},{"id":"P14-Yandex-Yandex Disk-P14.04","name":"P14.04","position":4,"score":"NA","value":"NA"},{"id":"P14-Yandex-Yandex Disk-P14.05","name":"P14.05","position":5,"score":"NA","value":"NA"},{"id":"P14-Yandex-Yandex Disk-P14.06","name":"P14.06","position":6,"score":"NA","value":"NA"},{"id":"P14-Yandex-Yandex Disk-P14.07","name":"P14.07","position":7,"score":"NA","value":"NA"},{"id":"P14-Yandex-Yandex Disk-P14.08","name":"P14.08","position":8,"score":"NA","value":"NA"},{"id":"P14-Yandex-Yandex Disk-P14.09","name":"P14.09","position":9,"score":"NA","value":"NA"},{"id":"P14-Yandex-Yandex Disk-P14.10","name":"P14.10","position":10,"score":"NA","value":"NA"},{"id":"P14-Yandex-Yandex Disk-P14.11","name":"P14.11","position":11,"score":"NA","value":"NA"}],"Yandex Search":[{"id":"P14-Yandex-Yandex Search-P14.01","name":"P14.01","position":1,"score":100,"value":"Yes"},{"id":"P14-Yandex-Yandex Search-P14.02","name":"P14.02","position":2,"score":100,"value":"Yes"},{"id":"P14-Yandex-Yandex Search-P14.03","name":"P14.03","position":3,"score":0,"value":"No Disclosure Found"},{"id":"P14-Yandex-Yandex Search-P14.04","name":"P14.04","position":4,"score":"NA","value":"NA"},{"id":"P14-Yandex-Yandex Search-P14.05","name":"P14.05","position":5,"score":"NA","value":"NA"},{"id":"P14-Yandex-Yandex Search-P14.06","name":"P14.06","position":6,"score":"NA","value":"NA"},{"id":"P14-Yandex-Yandex Search-P14.07","name":"P14.07","position":7,"score":"NA","value":"NA"},{"id":"P14-Yandex-Yandex Search-P14.08","name":"P14.08","position":8,"score":"NA","value":"NA"},{"id":"P14-Yandex-Yandex Search-P14.09","name":"P14.09","position":9,"score":"NA","value":"NA"},{"id":"P14-Yandex-Yandex Search-P14.10","name":"P14.10","position":10,"score":"NA","value":"NA"},{"id":"P14-Yandex-Yandex Search-P14.11","name":"P14.11","position":11,"score":"NA","value":"NA"}],"Yandex Mail":[{"id":"P14-Yandex-Yandex Mail-P14.01","name":"P14.01","position":1,"score":100,"value":"Yes"},{"id":"P14-Yandex-Yandex Mail-P14.02","name":"P14.02","position":2,"score":100,"value":"Yes"},{"id":"P14-Yandex-Yandex Mail-P14.03","name":"P14.03","position":3,"score":0,"value":"No Disclosure Found"},{"id":"P14-Yandex-Yandex Mail-P14.04","name":"P14.04","position":4,"score":"NA","value":"NA"},{"id":"P14-Yandex-Yandex Mail-P14.05","name":"P14.05","position":5,"score":"NA","value":"NA"},{"id":"P14-Yandex-Yandex Mail-P14.06","name":"P14.06","position":6,"score":"NA","value":"NA"},{"id":"P14-Yandex-Yandex Mail-P14.07","name":"P14.07","position":7,"score":"NA","value":"NA"},{"id":"P14-Yandex-Yandex Mail-P14.08","name":"P14.08","position":8,"score":"NA","value":"NA"},{"id":"P14-Yandex-Yandex Mail-P14.09","name":"P14.09","position":9,"score":"NA","value":"NA"},{"id":"P14-Yandex-Yandex Mail-P14.10","name":"P14.10","position":10,"score":"NA","value":"NA"},{"id":"P14-Yandex-Yandex Mail-P14.11","name":"P14.11","position":11,"score":"NA","value":"NA"}]},"Vodafone":{"Fixed-line broadband":[{"id":"P14-Vodafone-Fixed-line broadband-P14.01","name":"P14.01","position":1,"score":100,"value":"Yes"},{"id":"P14-Vodafone-Fixed-line broadband-P14.02","name":"P14.02","position":2,"score":100,"value":"Yes"},{"id":"P14-Vodafone-Fixed-line broadband-P14.03","name":"P14.03","position":3,"score":0,"value":"No Disclosure Found"},{"id":"P14-Vodafone-Fixed-line broadband-P14.04","name":"P14.04","position":4,"score":"NA","value":"NA"},{"id":"P14-Vodafone-Fixed-line broadband-P14.05","name":"P14.05","position":5,"score":"NA","value":"NA"},{"id":"P14-Vodafone-Fixed-line broadband-P14.06","name":"P14.06","position":6,"score":"NA","value":"NA"},{"id":"P14-Vodafone-Fixed-line broadband-P14.07","name":"P14.07","position":7,"score":"NA","value":"NA"},{"id":"P14-Vodafone-Fixed-line broadband-P14.08","name":"P14.08","position":8,"score":"NA","value":"NA"},{"id":"P14-Vodafone-Fixed-line broadband-P14.09","name":"P14.09","position":9,"score":"NA","value":"NA"},{"id":"P14-Vodafone-Fixed-line broadband-P14.10","name":"P14.10","position":10,"score":"NA","value":"NA"},{"id":"P14-Vodafone-Fixed-line broadband-P14.11","name":"P14.11","position":11,"score":"NA","value":"NA"}],"Postpaid mobile":[{"id":"P14-Vodafone-Postpaid mobile-P14.01","name":"P14.01","position":1,"score":100,"value":"Yes"},{"id":"P14-Vodafone-Postpaid mobile-P14.02","name":"P14.02","position":2,"score":100,"value":"Yes"},{"id":"P14-Vodafone-Postpaid mobile-P14.03","name":"P14.03","position":3,"score":0,"value":"No Disclosure Found"},{"id":"P14-Vodafone-Postpaid mobile-P14.04","name":"P14.04","position":4,"score":"NA","value":"NA"},{"id":"P14-Vodafone-Postpaid mobile-P14.05","name":"P14.05","position":5,"score":0,"value":"No Disclosure Found"},{"id":"P14-Vodafone-Postpaid mobile-P14.06","name":"P14.06","position":6,"score":0,"value":"No Disclosure Found"},{"id":"P14-Vodafone-Postpaid mobile-P14.07","name":"P14.07","position":7,"score":"NA","value":"NA"},{"id":"P14-Vodafone-Postpaid mobile-P14.08","name":"P14.08","position":8,"score":"NA","value":"NA"},{"id":"P14-Vodafone-Postpaid mobile-P14.09","name":"P14.09","position":9,"score":0,"value":"No Disclosure Found"},{"id":"P14-Vodafone-Postpaid mobile-P14.10","name":"P14.10","position":10,"score":"NA","value":"NA"},{"id":"P14-Vodafone-Postpaid mobile-P14.11","name":"P14.11","position":11,"score":"NA","value":"NA"}],"Prepaid mobile":[{"id":"P14-Vodafone-Prepaid mobile-P14.01","name":"P14.01","position":1,"score":100,"value":"Yes"},{"id":"P14-Vodafone-Prepaid mobile-P14.02","name":"P14.02","position":2,"score":100,"value":"Yes"},{"id":"P14-Vodafone-Prepaid mobile-P14.03","name":"P14.03","position":3,"score":0,"value":"No Disclosure Found"},{"id":"P14-Vodafone-Prepaid mobile-P14.04","name":"P14.04","position":4,"score":"NA","value":"NA"},{"id":"P14-Vodafone-Prepaid mobile-P14.05","name":"P14.05","position":5,"score":0,"value":"No Disclosure Found"},{"id":"P14-Vodafone-Prepaid mobile-P14.06","name":"P14.06","position":6,"score":0,"value":"No Disclosure Found"},{"id":"P14-Vodafone-Prepaid mobile-P14.07","name":"P14.07","position":7,"score":"NA","value":"NA"},{"id":"P14-Vodafone-Prepaid mobile-P14.08","name":"P14.08","position":8,"score":"NA","value":"NA"},{"id":"P14-Vodafone-Prepaid mobile-P14.09","name":"P14.09","position":9,"score":0,"value":"No Disclosure Found"},{"id":"P14-Vodafone-Prepaid mobile-P14.10","name":"P14.10","position":10,"score":"NA","value":"NA"},{"id":"P14-Vodafone-Prepaid mobile-P14.11","name":"P14.11","position":11,"score":"NA","value":"NA"}]},"VerizonMedia":{"Yahoo Mail":[{"id":"P14-VerizonMedia-Yahoo Mail-P14.01","name":"P14.01","position":1,"score":100,"value":"Yes"},{"id":"P14-VerizonMedia-Yahoo Mail-P14.02","name":"P14.02","position":2,"score":100,"value":"Yes"},{"id":"P14-VerizonMedia-Yahoo Mail-P14.03","name":"P14.03","position":3,"score":100,"value":"Yes"},{"id":"P14-VerizonMedia-Yahoo Mail-P14.04","name":"P14.04","position":4,"score":"NA","value":"NA"},{"id":"P14-VerizonMedia-Yahoo Mail-P14.05","name":"P14.05","position":5,"score":"NA","value":"NA"},{"id":"P14-VerizonMedia-Yahoo Mail-P14.06","name":"P14.06","position":6,"score":"NA","value":"NA"},{"id":"P14-VerizonMedia-Yahoo Mail-P14.07","name":"P14.07","position":7,"score":"NA","value":"NA"},{"id":"P14-VerizonMedia-Yahoo Mail-P14.08","name":"P14.08","position":8,"score":"NA","value":"NA"},{"id":"P14-VerizonMedia-Yahoo Mail-P14.09","name":"P14.09","position":9,"score":"NA","value":"NA"},{"id":"P14-VerizonMedia-Yahoo Mail-P14.10","name":"P14.10","position":10,"score":"NA","value":"NA"},{"id":"P14-VerizonMedia-Yahoo Mail-P14.11","name":"P14.11","position":11,"score":"NA","value":"NA"}]},"Twitter":{"Twitter":[{"id":"P14-Twitter-Twitter-P14.01","name":"P14.01","position":1,"score":100,"value":"Yes"},{"id":"P14-Twitter-Twitter-P14.02","name":"P14.02","position":2,"score":50,"value":"Partial"},{"id":"P14-Twitter-Twitter-P14.03","name":"P14.03","position":3,"score":0,"value":"No Disclosure Found"},{"id":"P14-Twitter-Twitter-P14.04","name":"P14.04","position":4,"score":"NA","value":"NA"},{"id":"P14-Twitter-Twitter-P14.05","name":"P14.05","position":5,"score":"NA","value":"NA"},{"id":"P14-Twitter-Twitter-P14.06","name":"P14.06","position":6,"score":"NA","value":"NA"},{"id":"P14-Twitter-Twitter-P14.07","name":"P14.07","position":7,"score":"NA","value":"NA"},{"id":"P14-Twitter-Twitter-P14.08","name":"P14.08","position":8,"score":"NA","value":"NA"},{"id":"P14-Twitter-Twitter-P14.09","name":"P14.09","position":9,"score":"NA","value":"NA"},{"id":"P14-Twitter-Twitter-P14.10","name":"P14.10","position":10,"score":"NA","value":"NA"},{"id":"P14-Twitter-Twitter-P14.11","name":"P14.11","position":11,"score":"NA","value":"NA"}]},"Tencent":{"Tencent Cloud":[{"id":"P14-Tencent-Tencent Cloud-P14.01","name":"P14.01","position":1,"score":100,"value":"Yes"},{"id":"P14-Tencent-Tencent Cloud-P14.02","name":"P14.02","position":2,"score":100,"value":"Yes"},{"id":"P14-Tencent-Tencent Cloud-P14.03","name":"P14.03","position":3,"score":0,"value":"No Disclosure Found"},{"id":"P14-Tencent-Tencent Cloud-P14.04","name":"P14.04","position":4,"score":"NA","value":"NA"},{"id":"P14-Tencent-Tencent Cloud-P14.05","name":"P14.05","position":5,"score":"NA","value":"NA"},{"id":"P14-Tencent-Tencent Cloud-P14.06","name":"P14.06","position":6,"score":"NA","value":"NA"},{"id":"P14-Tencent-Tencent Cloud-P14.07","name":"P14.07","position":7,"score":"NA","value":"NA"},{"id":"P14-Tencent-Tencent Cloud-P14.08","name":"P14.08","position":8,"score":"NA","value":"NA"},{"id":"P14-Tencent-Tencent Cloud-P14.09","name":"P14.09","position":9,"score":"NA","value":"NA"},{"id":"P14-Tencent-Tencent Cloud-P14.10","name":"P14.10","position":10,"score":"NA","value":"NA"},{"id":"P14-Tencent-Tencent Cloud-P14.11","name":"P14.11","position":11,"score":"NA","value":"NA"}],"WeChat":[{"id":"P14-Tencent-WeChat-P14.01","name":"P14.01","position":1,"score":100,"value":"Yes"},{"id":"P14-Tencent-WeChat-P14.02","name":"P14.02","position":2,"score":100,"value":"Yes"},{"id":"P14-Tencent-WeChat-P14.03","name":"P14.03","position":3,"score":0,"value":"No Disclosure Found"},{"id":"P14-Tencent-WeChat-P14.04","name":"P14.04","position":4,"score":"NA","value":"NA"},{"id":"P14-Tencent-WeChat-P14.05","name":"P14.05","position":5,"score":"NA","value":"NA"},{"id":"P14-Tencent-WeChat-P14.06","name":"P14.06","position":6,"score":"NA","value":"NA"},{"id":"P14-Tencent-WeChat-P14.07","name":"P14.07","position":7,"score":"NA","value":"NA"},{"id":"P14-Tencent-WeChat-P14.08","name":"P14.08","position":8,"score":"NA","value":"NA"},{"id":"P14-Tencent-WeChat-P14.09","name":"P14.09","position":9,"score":"NA","value":"NA"},{"id":"P14-Tencent-WeChat-P14.10","name":"P14.10","position":10,"score":"NA","value":"NA"},{"id":"P14-Tencent-WeChat-P14.11","name":"P14.11","position":11,"score":"NA","value":"NA"}],"QQ":[{"id":"P14-Tencent-QQ-P14.01","name":"P14.01","position":1,"score":100,"value":"Yes"},{"id":"P14-Tencent-QQ-P14.02","name":"P14.02","position":2,"score":100,"value":"Yes"},{"id":"P14-Tencent-QQ-P14.03","name":"P14.03","position":3,"score":0,"value":"No Disclosure Found"},{"id":"P14-Tencent-QQ-P14.04","name":"P14.04","position":4,"score":"NA","value":"NA"},{"id":"P14-Tencent-QQ-P14.05","name":"P14.05","position":5,"score":"NA","value":"NA"},{"id":"P14-Tencent-QQ-P14.06","name":"P14.06","position":6,"score":"NA","value":"NA"},{"id":"P14-Tencent-QQ-P14.07","name":"P14.07","position":7,"score":"NA","value":"NA"},{"id":"P14-Tencent-QQ-P14.08","name":"P14.08","position":8,"score":"NA","value":"NA"},{"id":"P14-Tencent-QQ-P14.09","name":"P14.09","position":9,"score":"NA","value":"NA"},{"id":"P14-Tencent-QQ-P14.10","name":"P14.10","position":10,"score":"NA","value":"NA"},{"id":"P14-Tencent-QQ-P14.11","name":"P14.11","position":11,"score":"NA","value":"NA"}],"QZone":[{"id":"P14-Tencent-QZone-P14.01","name":"P14.01","position":1,"score":100,"value":"Yes"},{"id":"P14-Tencent-QZone-P14.02","name":"P14.02","position":2,"score":100,"value":"Yes"},{"id":"P14-Tencent-QZone-P14.03","name":"P14.03","position":3,"score":0,"value":"No Disclosure Found"},{"id":"P14-Tencent-QZone-P14.04","name":"P14.04","position":4,"score":"NA","value":"NA"},{"id":"P14-Tencent-QZone-P14.05","name":"P14.05","position":5,"score":"NA","value":"NA"},{"id":"P14-Tencent-QZone-P14.06","name":"P14.06","position":6,"score":"NA","value":"NA"},{"id":"P14-Tencent-QZone-P14.07","name":"P14.07","position":7,"score":"NA","value":"NA"},{"id":"P14-Tencent-QZone-P14.08","name":"P14.08","position":8,"score":"NA","value":"NA"},{"id":"P14-Tencent-QZone-P14.09","name":"P14.09","position":9,"score":"NA","value":"NA"},{"id":"P14-Tencent-QZone-P14.10","name":"P14.10","position":10,"score":"NA","value":"NA"},{"id":"P14-Tencent-QZone-P14.11","name":"P14.11","position":11,"score":"NA","value":"NA"}]},"Telenor":{"Fixed-line broadband":[{"id":"P14-Telenor-Fixed-line broadband-P14.01","name":"P14.01","position":1,"score":0,"value":"No Disclosure Found"},{"id":"P14-Telenor-Fixed-line broadband-P14.02","name":"P14.02","position":2,"score":0,"value":"No Disclosure Found"},{"id":"P14-Telenor-Fixed-line broadband-P14.03","name":"P14.03","position":3,"score":0,"value":"No Disclosure Found"},{"id":"P14-Telenor-Fixed-line broadband-P14.04","name":"P14.04","position":4,"score":"NA","value":"NA"},{"id":"P14-Telenor-Fixed-line broadband-P14.05","name":"P14.05","position":5,"score":"NA","value":"NA"},{"id":"P14-Telenor-Fixed-line broadband-P14.06","name":"P14.06","position":6,"score":"NA","value":"NA"},{"id":"P14-Telenor-Fixed-line broadband-P14.07","name":"P14.07","position":7,"score":"NA","value":"NA"},{"id":"P14-Telenor-Fixed-line broadband-P14.08","name":"P14.08","position":8,"score":"NA","value":"NA"},{"id":"P14-Telenor-Fixed-line broadband-P14.09","name":"P14.09","position":9,"score":"NA","value":"NA"},{"id":"P14-Telenor-Fixed-line broadband-P14.10","name":"P14.10","position":10,"score":"NA","value":"NA"},{"id":"P14-Telenor-Fixed-line broadband-P14.11","name":"P14.11","position":11,"score":"NA","value":"NA"}],"Postpaid mobile":[{"id":"P14-Telenor-Postpaid mobile-P14.01","name":"P14.01","position":1,"score":0,"value":"No Disclosure Found"},{"id":"P14-Telenor-Postpaid mobile-P14.02","name":"P14.02","position":2,"score":0,"value":"No Disclosure Found"},{"id":"P14-Telenor-Postpaid mobile-P14.03","name":"P14.03","position":3,"score":0,"value":"No Disclosure Found"},{"id":"P14-Telenor-Postpaid mobile-P14.04","name":"P14.04","position":4,"score":"NA","value":"NA"},{"id":"P14-Telenor-Postpaid mobile-P14.05","name":"P14.05","position":5,"score":50,"value":"Partial"},{"id":"P14-Telenor-Postpaid mobile-P14.06","name":"P14.06","position":6,"score":0,"value":"No Disclosure Found"},{"id":"P14-Telenor-Postpaid mobile-P14.07","name":"P14.07","position":7,"score":"NA","value":"NA"},{"id":"P14-Telenor-Postpaid mobile-P14.08","name":"P14.08","position":8,"score":"NA","value":"NA"},{"id":"P14-Telenor-Postpaid mobile-P14.09","name":"P14.09","position":9,"score":0,"value":"No Disclosure Found"},{"id":"P14-Telenor-Postpaid mobile-P14.10","name":"P14.10","position":10,"score":"NA","value":"NA"},{"id":"P14-Telenor-Postpaid mobile-P14.11","name":"P14.11","position":11,"score":"NA","value":"NA"}],"Prepaid mobile":[{"id":"P14-Telenor-Prepaid mobile-P14.01","name":"P14.01","position":1,"score":0,"value":"No Disclosure Found"},{"id":"P14-Telenor-Prepaid mobile-P14.02","name":"P14.02","position":2,"score":0,"value":"No Disclosure Found"},{"id":"P14-Telenor-Prepaid mobile-P14.03","name":"P14.03","position":3,"score":0,"value":"No Disclosure Found"},{"id":"P14-Telenor-Prepaid mobile-P14.04","name":"P14.04","position":4,"score":"NA","value":"NA"},{"id":"P14-Telenor-Prepaid mobile-P14.05","name":"P14.05","position":5,"score":50,"value":"Partial"},{"id":"P14-Telenor-Prepaid mobile-P14.06","name":"P14.06","position":6,"score":0,"value":"No Disclosure Found"},{"id":"P14-Telenor-Prepaid mobile-P14.07","name":"P14.07","position":7,"score":"NA","value":"NA"},{"id":"P14-Telenor-Prepaid mobile-P14.08","name":"P14.08","position":8,"score":"NA","value":"NA"},{"id":"P14-Telenor-Prepaid mobile-P14.09","name":"P14.09","position":9,"score":0,"value":"No Disclosure Found"},{"id":"P14-Telenor-Prepaid mobile-P14.10","name":"P14.10","position":10,"score":"NA","value":"NA"},{"id":"P14-Telenor-Prepaid mobile-P14.11","name":"P14.11","position":11,"score":"NA","value":"NA"}]},"Telefonica":{"Fixed-line broadband":[{"id":"P14-Telefonica-Fixed-line broadband-P14.01","name":"P14.01","position":1,"score":100,"value":"Yes"},{"id":"P14-Telefonica-Fixed-line broadband-P14.02","name":"P14.02","position":2,"score":0,"value":"No Disclosure Found"},{"id":"P14-Telefonica-Fixed-line broadband-P14.03","name":"P14.03","position":3,"score":0,"value":"No Disclosure Found"},{"id":"P14-Telefonica-Fixed-line broadband-P14.04","name":"P14.04","position":4,"score":"NA","value":"NA"},{"id":"P14-Telefonica-Fixed-line broadband-P14.05","name":"P14.05","position":5,"score":"NA","value":"NA"},{"id":"P14-Telefonica-Fixed-line broadband-P14.06","name":"P14.06","position":6,"score":"NA","value":"NA"},{"id":"P14-Telefonica-Fixed-line broadband-P14.07","name":"P14.07","position":7,"score":"NA","value":"NA"},{"id":"P14-Telefonica-Fixed-line broadband-P14.08","name":"P14.08","position":8,"score":"NA","value":"NA"},{"id":"P14-Telefonica-Fixed-line broadband-P14.09","name":"P14.09","position":9,"score":"NA","value":"NA"},{"id":"P14-Telefonica-Fixed-line broadband-P14.10","name":"P14.10","position":10,"score":"NA","value":"NA"},{"id":"P14-Telefonica-Fixed-line broadband-P14.11","name":"P14.11","position":11,"score":"NA","value":"NA"}],"Postpaid mobile":[{"id":"P14-Telefonica-Postpaid mobile-P14.01","name":"P14.01","position":1,"score":100,"value":"Yes"},{"id":"P14-Telefonica-Postpaid mobile-P14.02","name":"P14.02","position":2,"score":0,"value":"No Disclosure Found"},{"id":"P14-Telefonica-Postpaid mobile-P14.03","name":"P14.03","position":3,"score":0,"value":"No Disclosure Found"},{"id":"P14-Telefonica-Postpaid mobile-P14.04","name":"P14.04","position":4,"score":"NA","value":"NA"},{"id":"P14-Telefonica-Postpaid mobile-P14.05","name":"P14.05","position":5,"score":0,"value":"No Disclosure Found"},{"id":"P14-Telefonica-Postpaid mobile-P14.06","name":"P14.06","position":6,"score":0,"value":"No Disclosure Found"},{"id":"P14-Telefonica-Postpaid mobile-P14.07","name":"P14.07","position":7,"score":"NA","value":"NA"},{"id":"P14-Telefonica-Postpaid mobile-P14.08","name":"P14.08","position":8,"score":"NA","value":"NA"},{"id":"P14-Telefonica-Postpaid mobile-P14.09","name":"P14.09","position":9,"score":0,"value":"No Disclosure Found"},{"id":"P14-Telefonica-Postpaid mobile-P14.10","name":"P14.10","position":10,"score":"NA","value":"NA"},{"id":"P14-Telefonica-Postpaid mobile-P14.11","name":"P14.11","position":11,"score":"NA","value":"NA"}],"Prepaid mobile":[{"id":"P14-Telefonica-Prepaid mobile-P14.01","name":"P14.01","position":1,"score":100,"value":"Yes"},{"id":"P14-Telefonica-Prepaid mobile-P14.02","name":"P14.02","position":2,"score":0,"value":"No Disclosure Found"},{"id":"P14-Telefonica-Prepaid mobile-P14.03","name":"P14.03","position":3,"score":0,"value":"No Disclosure Found"},{"id":"P14-Telefonica-Prepaid mobile-P14.04","name":"P14.04","position":4,"score":"NA","value":"NA"},{"id":"P14-Telefonica-Prepaid mobile-P14.05","name":"P14.05","position":5,"score":0,"value":"No Disclosure Found"},{"id":"P14-Telefonica-Prepaid mobile-P14.06","name":"P14.06","position":6,"score":0,"value":"No Disclosure Found"},{"id":"P14-Telefonica-Prepaid mobile-P14.07","name":"P14.07","position":7,"score":"NA","value":"NA"},{"id":"P14-Telefonica-Prepaid mobile-P14.08","name":"P14.08","position":8,"score":"NA","value":"NA"},{"id":"P14-Telefonica-Prepaid mobile-P14.09","name":"P14.09","position":9,"score":0,"value":"No Disclosure Found"},{"id":"P14-Telefonica-Prepaid mobile-P14.10","name":"P14.10","position":10,"score":"NA","value":"NA"},{"id":"P14-Telefonica-Prepaid mobile-P14.11","name":"P14.11","position":11,"score":"NA","value":"NA"}]},"Samsung":{"Samsung Cloud":[{"id":"P14-Samsung-Samsung Cloud-P14.01","name":"P14.01","position":1,"score":0,"value":"No"},{"id":"P14-Samsung-Samsung Cloud-P14.02","name":"P14.02","position":2,"score":0,"value":"No"},{"id":"P14-Samsung-Samsung Cloud-P14.03","name":"P14.03","position":3,"score":0,"value":"No Disclosure Found"},{"id":"P14-Samsung-Samsung Cloud-P14.04","name":"P14.04","position":4,"score":"NA","value":"NA"},{"id":"P14-Samsung-Samsung Cloud-P14.05","name":"P14.05","position":5,"score":"NA","value":"NA"},{"id":"P14-Samsung-Samsung Cloud-P14.06","name":"P14.06","position":6,"score":"NA","value":"NA"},{"id":"P14-Samsung-Samsung Cloud-P14.07","name":"P14.07","position":7,"score":"NA","value":"NA"},{"id":"P14-Samsung-Samsung Cloud-P14.08","name":"P14.08","position":8,"score":"NA","value":"NA"},{"id":"P14-Samsung-Samsung Cloud-P14.09","name":"P14.09","position":9,"score":"NA","value":"NA"},{"id":"P14-Samsung-Samsung Cloud-P14.10","name":"P14.10","position":10,"score":"NA","value":"NA"},{"id":"P14-Samsung-Samsung Cloud-P14.11","name":"P14.11","position":11,"score":"NA","value":"NA"}],"Samsung implementation of Android":[{"id":"P14-Samsung-Samsung implementation of Android-P14.01","name":"P14.01","position":1,"score":100,"value":"Yes"},{"id":"P14-Samsung-Samsung implementation of Android-P14.02","name":"P14.02","position":2,"score":100,"value":"Yes"},{"id":"P14-Samsung-Samsung implementation of Android-P14.03","name":"P14.03","position":3,"score":0,"value":"No Disclosure Found"},{"id":"P14-Samsung-Samsung implementation of Android-P14.04","name":"P14.04","position":4,"score":100,"value":"Yes"},{"id":"P14-Samsung-Samsung implementation of Android-P14.05","name":"P14.05","position":5,"score":0,"value":"No Disclosure Found"},{"id":"P14-Samsung-Samsung implementation of Android-P14.06","name":"P14.06","position":6,"score":100,"value":"Yes"},{"id":"P14-Samsung-Samsung implementation of Android-P14.07","name":"P14.07","position":7,"score":0,"value":"No Disclosure Found"},{"id":"P14-Samsung-Samsung implementation of Android-P14.08","name":"P14.08","position":8,"score":0,"value":"No Disclosure Found"},{"id":"P14-Samsung-Samsung implementation of Android-P14.09","name":"P14.09","position":9,"score":0,"value":"No Disclosure Found"},{"id":"P14-Samsung-Samsung implementation of Android-P14.10","name":"P14.10","position":10,"score":"NA","value":"NA"},{"id":"P14-Samsung-Samsung implementation of Android-P14.11","name":"P14.11","position":11,"score":"NA","value":"NA"}]},"Orange":{"Fixed-line broadband":[{"id":"P14-Orange-Fixed-line broadband-P14.01","name":"P14.01","position":1,"score":100,"value":"Yes"},{"id":"P14-Orange-Fixed-line broadband-P14.02","name":"P14.02","position":2,"score":0,"value":"No Disclosure Found"},{"id":"P14-Orange-Fixed-line broadband-P14.03","name":"P14.03","position":3,"score":0,"value":"No Disclosure Found"},{"id":"P14-Orange-Fixed-line broadband-P14.04","name":"P14.04","position":4,"score":"NA","value":"NA"},{"id":"P14-Orange-Fixed-line broadband-P14.05","name":"P14.05","position":5,"score":"NA","value":"NA"},{"id":"P14-Orange-Fixed-line broadband-P14.06","name":"P14.06","position":6,"score":"NA","value":"NA"},{"id":"P14-Orange-Fixed-line broadband-P14.07","name":"P14.07","position":7,"score":"NA","value":"NA"},{"id":"P14-Orange-Fixed-line broadband-P14.08","name":"P14.08","position":8,"score":"NA","value":"NA"},{"id":"P14-Orange-Fixed-line broadband-P14.09","name":"P14.09","position":9,"score":"NA","value":"NA"},{"id":"P14-Orange-Fixed-line broadband-P14.10","name":"P14.10","position":10,"score":"NA","value":"NA"},{"id":"P14-Orange-Fixed-line broadband-P14.11","name":"P14.11","position":11,"score":"NA","value":"NA"}],"Postpaid mobile":[{"id":"P14-Orange-Postpaid mobile-P14.01","name":"P14.01","position":1,"score":100,"value":"Yes"},{"id":"P14-Orange-Postpaid mobile-P14.02","name":"P14.02","position":2,"score":0,"value":"No Disclosure Found"},{"id":"P14-Orange-Postpaid mobile-P14.03","name":"P14.03","position":3,"score":0,"value":"No Disclosure Found"},{"id":"P14-Orange-Postpaid mobile-P14.04","name":"P14.04","position":4,"score":"NA","value":"NA"},{"id":"P14-Orange-Postpaid mobile-P14.05","name":"P14.05","position":5,"score":0,"value":"No Disclosure Found"},{"id":"P14-Orange-Postpaid mobile-P14.06","name":"P14.06","position":6,"score":0,"value":"No Disclosure Found"},{"id":"P14-Orange-Postpaid mobile-P14.07","name":"P14.07","position":7,"score":"NA","value":"NA"},{"id":"P14-Orange-Postpaid mobile-P14.08","name":"P14.08","position":8,"score":"NA","value":"NA"},{"id":"P14-Orange-Postpaid mobile-P14.09","name":"P14.09","position":9,"score":0,"value":"No Disclosure Found"},{"id":"P14-Orange-Postpaid mobile-P14.10","name":"P14.10","position":10,"score":"NA","value":"NA"},{"id":"P14-Orange-Postpaid mobile-P14.11","name":"P14.11","position":11,"score":"NA","value":"NA"}],"Prepaid mobile":[{"id":"P14-Orange-Prepaid mobile-P14.01","name":"P14.01","position":1,"score":100,"value":"Yes"},{"id":"P14-Orange-Prepaid mobile-P14.02","name":"P14.02","position":2,"score":0,"value":"No Disclosure Found"},{"id":"P14-Orange-Prepaid mobile-P14.03","name":"P14.03","position":3,"score":0,"value":"No Disclosure Found"},{"id":"P14-Orange-Prepaid mobile-P14.04","name":"P14.04","position":4,"score":"NA","value":"NA"},{"id":"P14-Orange-Prepaid mobile-P14.05","name":"P14.05","position":5,"score":0,"value":"No Disclosure Found"},{"id":"P14-Orange-Prepaid mobile-P14.06","name":"P14.06","position":6,"score":0,"value":"No Disclosure Found"},{"id":"P14-Orange-Prepaid mobile-P14.07","name":"P14.07","position":7,"score":"NA","value":"NA"},{"id":"P14-Orange-Prepaid mobile-P14.08","name":"P14.08","position":8,"score":"NA","value":"NA"},{"id":"P14-Orange-Prepaid mobile-P14.09","name":"P14.09","position":9,"score":0,"value":"No Disclosure Found"},{"id":"P14-Orange-Prepaid mobile-P14.10","name":"P14.10","position":10,"score":"NA","value":"NA"},{"id":"P14-Orange-Prepaid mobile-P14.11","name":"P14.11","position":11,"score":"NA","value":"NA"}]},"Ooredoo":{"Fixed-line broadband":[{"id":"P14-Ooredoo-Fixed-line broadband-P14.01","name":"P14.01","position":1,"score":0,"value":"No Disclosure Found"},{"id":"P14-Ooredoo-Fixed-line broadband-P14.02","name":"P14.02","position":2,"score":0,"value":"No Disclosure Found"},{"id":"P14-Ooredoo-Fixed-line broadband-P14.03","name":"P14.03","position":3,"score":0,"value":"No Disclosure Found"},{"id":"P14-Ooredoo-Fixed-line broadband-P14.04","name":"P14.04","position":4,"score":"NA","value":"NA"},{"id":"P14-Ooredoo-Fixed-line broadband-P14.05","name":"P14.05","position":5,"score":"NA","value":"NA"},{"id":"P14-Ooredoo-Fixed-line broadband-P14.06","name":"P14.06","position":6,"score":"NA","value":"NA"},{"id":"P14-Ooredoo-Fixed-line broadband-P14.07","name":"P14.07","position":7,"score":"NA","value":"NA"},{"id":"P14-Ooredoo-Fixed-line broadband-P14.08","name":"P14.08","position":8,"score":"NA","value":"NA"},{"id":"P14-Ooredoo-Fixed-line broadband-P14.09","name":"P14.09","position":9,"score":"NA","value":"NA"},{"id":"P14-Ooredoo-Fixed-line broadband-P14.10","name":"P14.10","position":10,"score":"NA","value":"NA"},{"id":"P14-Ooredoo-Fixed-line broadband-P14.11","name":"P14.11","position":11,"score":"NA","value":"NA"}],"Postpaid mobile":[{"id":"P14-Ooredoo-Postpaid mobile-P14.01","name":"P14.01","position":1,"score":0,"value":"No Disclosure Found"},{"id":"P14-Ooredoo-Postpaid mobile-P14.02","name":"P14.02","position":2,"score":0,"value":"No Disclosure Found"},{"id":"P14-Ooredoo-Postpaid mobile-P14.03","name":"P14.03","position":3,"score":0,"value":"No Disclosure Found"},{"id":"P14-Ooredoo-Postpaid mobile-P14.04","name":"P14.04","position":4,"score":"NA","value":"NA"},{"id":"P14-Ooredoo-Postpaid mobile-P14.05","name":"P14.05","position":5,"score":0,"value":"No Disclosure Found"},{"id":"P14-Ooredoo-Postpaid mobile-P14.06","name":"P14.06","position":6,"score":0,"value":"No Disclosure Found"},{"id":"P14-Ooredoo-Postpaid mobile-P14.07","name":"P14.07","position":7,"score":"NA","value":"NA"},{"id":"P14-Ooredoo-Postpaid mobile-P14.08","name":"P14.08","position":8,"score":"NA","value":"NA"},{"id":"P14-Ooredoo-Postpaid mobile-P14.09","name":"P14.09","position":9,"score":0,"value":"No Disclosure Found"},{"id":"P14-Ooredoo-Postpaid mobile-P14.10","name":"P14.10","position":10,"score":"NA","value":"NA"},{"id":"P14-Ooredoo-Postpaid mobile-P14.11","name":"P14.11","position":11,"score":"NA","value":"NA"}],"Prepaid mobile":[{"id":"P14-Ooredoo-Prepaid mobile-P14.01","name":"P14.01","position":1,"score":0,"value":"No Disclosure Found"},{"id":"P14-Ooredoo-Prepaid mobile-P14.02","name":"P14.02","position":2,"score":0,"value":"No Disclosure Found"},{"id":"P14-Ooredoo-Prepaid mobile-P14.03","name":"P14.03","position":3,"score":0,"value":"No Disclosure Found"},{"id":"P14-Ooredoo-Prepaid mobile-P14.04","name":"P14.04","position":4,"score":"NA","value":"NA"},{"id":"P14-Ooredoo-Prepaid mobile-P14.05","name":"P14.05","position":5,"score":0,"value":"No Disclosure Found"},{"id":"P14-Ooredoo-Prepaid mobile-P14.06","name":"P14.06","position":6,"score":0,"value":"No Disclosure Found"},{"id":"P14-Ooredoo-Prepaid mobile-P14.07","name":"P14.07","position":7,"score":"NA","value":"NA"},{"id":"P14-Ooredoo-Prepaid mobile-P14.08","name":"P14.08","position":8,"score":"NA","value":"NA"},{"id":"P14-Ooredoo-Prepaid mobile-P14.09","name":"P14.09","position":9,"score":0,"value":"No Disclosure Found"},{"id":"P14-Ooredoo-Prepaid mobile-P14.10","name":"P14.10","position":10,"score":"NA","value":"NA"},{"id":"P14-Ooredoo-Prepaid mobile-P14.11","name":"P14.11","position":11,"score":"NA","value":"NA"}]},"MTN":{"Fixed-line broadband":[{"id":"P14-MTN-Fixed-line broadband-P14.01","name":"P14.01","position":1,"score":100,"value":"Yes"},{"id":"P14-MTN-Fixed-line broadband-P14.02","name":"P14.02","position":2,"score":100,"value":"Yes"},{"id":"P14-MTN-Fixed-line broadband-P14.03","name":"P14.03","position":3,"score":100,"value":"Yes"},{"id":"P14-MTN-Fixed-line broadband-P14.04","name":"P14.04","position":4,"score":"NA","value":"NA"},{"id":"P14-MTN-Fixed-line broadband-P14.05","name":"P14.05","position":5,"score":"NA","value":"NA"},{"id":"P14-MTN-Fixed-line broadband-P14.06","name":"P14.06","position":6,"score":"NA","value":"NA"},{"id":"P14-MTN-Fixed-line broadband-P14.07","name":"P14.07","position":7,"score":"NA","value":"NA"},{"id":"P14-MTN-Fixed-line broadband-P14.08","name":"P14.08","position":8,"score":"NA","value":"NA"},{"id":"P14-MTN-Fixed-line broadband-P14.09","name":"P14.09","position":9,"score":"NA","value":"NA"},{"id":"P14-MTN-Fixed-line broadband-P14.10","name":"P14.10","position":10,"score":"NA","value":"NA"},{"id":"P14-MTN-Fixed-line broadband-P14.11","name":"P14.11","position":11,"score":"NA","value":"NA"}],"Postpaid mobile":[{"id":"P14-MTN-Postpaid mobile-P14.01","name":"P14.01","position":1,"score":100,"value":"Yes"},{"id":"P14-MTN-Postpaid mobile-P14.02","name":"P14.02","position":2,"score":100,"value":"Yes"},{"id":"P14-MTN-Postpaid mobile-P14.03","name":"P14.03","position":3,"score":100,"value":"Yes"},{"id":"P14-MTN-Postpaid mobile-P14.04","name":"P14.04","position":4,"score":"NA","value":"NA"},{"id":"P14-MTN-Postpaid mobile-P14.05","name":"P14.05","position":5,"score":0,"value":"No Disclosure Found"},{"id":"P14-MTN-Postpaid mobile-P14.06","name":"P14.06","position":6,"score":0,"value":"No Disclosure Found"},{"id":"P14-MTN-Postpaid mobile-P14.07","name":"P14.07","position":7,"score":"NA","value":"NA"},{"id":"P14-MTN-Postpaid mobile-P14.08","name":"P14.08","position":8,"score":"NA","value":"NA"},{"id":"P14-MTN-Postpaid mobile-P14.09","name":"P14.09","position":9,"score":0,"value":"No Disclosure Found"},{"id":"P14-MTN-Postpaid mobile-P14.10","name":"P14.10","position":10,"score":"NA","value":"NA"},{"id":"P14-MTN-Postpaid mobile-P14.11","name":"P14.11","position":11,"score":"NA","value":"NA"}],"Prepaid mobile":[{"id":"P14-MTN-Prepaid mobile-P14.01","name":"P14.01","position":1,"score":100,"value":"Yes"},{"id":"P14-MTN-Prepaid mobile-P14.02","name":"P14.02","position":2,"score":100,"value":"Yes"},{"id":"P14-MTN-Prepaid mobile-P14.03","name":"P14.03","position":3,"score":100,"value":"Yes"},{"id":"P14-MTN-Prepaid mobile-P14.04","name":"P14.04","position":4,"score":"NA","value":"NA"},{"id":"P14-MTN-Prepaid mobile-P14.05","name":"P14.05","position":5,"score":0,"value":"No Disclosure Found"},{"id":"P14-MTN-Prepaid mobile-P14.06","name":"P14.06","position":6,"score":0,"value":"No Disclosure Found"},{"id":"P14-MTN-Prepaid mobile-P14.07","name":"P14.07","position":7,"score":"NA","value":"NA"},{"id":"P14-MTN-Prepaid mobile-P14.08","name":"P14.08","position":8,"score":"NA","value":"NA"},{"id":"P14-MTN-Prepaid mobile-P14.09","name":"P14.09","position":9,"score":0,"value":"No Disclosure Found"},{"id":"P14-MTN-Prepaid mobile-P14.10","name":"P14.10","position":10,"score":"NA","value":"NA"},{"id":"P14-MTN-Prepaid mobile-P14.11","name":"P14.11","position":11,"score":"NA","value":"NA"}]},"Microsoft":{"OneDrive":[{"id":"P14-Microsoft-OneDrive-P14.01","name":"P14.01","position":1,"score":100,"value":"Yes"},{"id":"P14-Microsoft-OneDrive-P14.02","name":"P14.02","position":2,"score":50,"value":"Partial"},{"id":"P14-Microsoft-OneDrive-P14.03","name":"P14.03","position":3,"score":100,"value":"Yes"},{"id":"P14-Microsoft-OneDrive-P14.04","name":"P14.04","position":4,"score":"NA","value":"NA"},{"id":"P14-Microsoft-OneDrive-P14.05","name":"P14.05","position":5,"score":"NA","value":"NA"},{"id":"P14-Microsoft-OneDrive-P14.06","name":"P14.06","position":6,"score":"NA","value":"NA"},{"id":"P14-Microsoft-OneDrive-P14.07","name":"P14.07","position":7,"score":"NA","value":"NA"},{"id":"P14-Microsoft-OneDrive-P14.08","name":"P14.08","position":8,"score":"NA","value":"NA"},{"id":"P14-Microsoft-OneDrive-P14.09","name":"P14.09","position":9,"score":"NA","value":"NA"},{"id":"P14-Microsoft-OneDrive-P14.10","name":"P14.10","position":10,"score":"NA","value":"NA"},{"id":"P14-Microsoft-OneDrive-P14.11","name":"P14.11","position":11,"score":"NA","value":"NA"}],"Skype":[{"id":"P14-Microsoft-Skype-P14.01","name":"P14.01","position":1,"score":100,"value":"Yes"},{"id":"P14-Microsoft-Skype-P14.02","name":"P14.02","position":2,"score":50,"value":"Partial"},{"id":"P14-Microsoft-Skype-P14.03","name":"P14.03","position":3,"score":100,"value":"Yes"},{"id":"P14-Microsoft-Skype-P14.04","name":"P14.04","position":4,"score":"NA","value":"NA"},{"id":"P14-Microsoft-Skype-P14.05","name":"P14.05","position":5,"score":"NA","value":"NA"},{"id":"P14-Microsoft-Skype-P14.06","name":"P14.06","position":6,"score":"NA","value":"NA"},{"id":"P14-Microsoft-Skype-P14.07","name":"P14.07","position":7,"score":"NA","value":"NA"},{"id":"P14-Microsoft-Skype-P14.08","name":"P14.08","position":8,"score":"NA","value":"NA"},{"id":"P14-Microsoft-Skype-P14.09","name":"P14.09","position":9,"score":"NA","value":"NA"},{"id":"P14-Microsoft-Skype-P14.10","name":"P14.10","position":10,"score":"NA","value":"NA"},{"id":"P14-Microsoft-Skype-P14.11","name":"P14.11","position":11,"score":"NA","value":"NA"}],"Outlook.com":[{"id":"P14-Microsoft-Outlook.com-P14.01","name":"P14.01","position":1,"score":100,"value":"Yes"},{"id":"P14-Microsoft-Outlook.com-P14.02","name":"P14.02","position":2,"score":50,"value":"Partial"},{"id":"P14-Microsoft-Outlook.com-P14.03","name":"P14.03","position":3,"score":100,"value":"Yes"},{"id":"P14-Microsoft-Outlook.com-P14.04","name":"P14.04","position":4,"score":"NA","value":"NA"},{"id":"P14-Microsoft-Outlook.com-P14.05","name":"P14.05","position":5,"score":"NA","value":"NA"},{"id":"P14-Microsoft-Outlook.com-P14.06","name":"P14.06","position":6,"score":"NA","value":"NA"},{"id":"P14-Microsoft-Outlook.com-P14.07","name":"P14.07","position":7,"score":"NA","value":"NA"},{"id":"P14-Microsoft-Outlook.com-P14.08","name":"P14.08","position":8,"score":"NA","value":"NA"},{"id":"P14-Microsoft-Outlook.com-P14.09","name":"P14.09","position":9,"score":"NA","value":"NA"},{"id":"P14-Microsoft-Outlook.com-P14.10","name":"P14.10","position":10,"score":"NA","value":"NA"},{"id":"P14-Microsoft-Outlook.com-P14.11","name":"P14.11","position":11,"score":"NA","value":"NA"}],"Bing":[{"id":"P14-Microsoft-Bing-P14.01","name":"P14.01","position":1,"score":100,"value":"Yes"},{"id":"P14-Microsoft-Bing-P14.02","name":"P14.02","position":2,"score":50,"value":"Partial"},{"id":"P14-Microsoft-Bing-P14.03","name":"P14.03","position":3,"score":100,"value":"Yes"},{"id":"P14-Microsoft-Bing-P14.04","name":"P14.04","position":4,"score":"NA","value":"NA"},{"id":"P14-Microsoft-Bing-P14.05","name":"P14.05","position":5,"score":"NA","value":"NA"},{"id":"P14-Microsoft-Bing-P14.06","name":"P14.06","position":6,"score":"NA","value":"NA"},{"id":"P14-Microsoft-Bing-P14.07","name":"P14.07","position":7,"score":"NA","value":"NA"},{"id":"P14-Microsoft-Bing-P14.08","name":"P14.08","position":8,"score":"NA","value":"NA"},{"id":"P14-Microsoft-Bing-P14.09","name":"P14.09","position":9,"score":"NA","value":"NA"},{"id":"P14-Microsoft-Bing-P14.10","name":"P14.10","position":10,"score":"NA","value":"NA"},{"id":"P14-Microsoft-Bing-P14.11","name":"P14.11","position":11,"score":"NA","value":"NA"}]},"MailRu":{"Mail.Ru Cloud Solutions":[{"id":"P14-MailRu-Mail.Ru Cloud Solutions-P14.01","name":"P14.01","position":1,"score":100,"value":"Yes"},{"id":"P14-MailRu-Mail.Ru Cloud Solutions-P14.02","name":"P14.02","position":2,"score":100,"value":"Yes"},{"id":"P14-MailRu-Mail.Ru Cloud Solutions-P14.03","name":"P14.03","position":3,"score":0,"value":"No Disclosure Found"},{"id":"P14-MailRu-Mail.Ru Cloud Solutions-P14.04","name":"P14.04","position":4,"score":"NA","value":"NA"},{"id":"P14-MailRu-Mail.Ru Cloud Solutions-P14.05","name":"P14.05","position":5,"score":"NA","value":"NA"},{"id":"P14-MailRu-Mail.Ru Cloud Solutions-P14.06","name":"P14.06","position":6,"score":"NA","value":"NA"},{"id":"P14-MailRu-Mail.Ru Cloud Solutions-P14.07","name":"P14.07","position":7,"score":"NA","value":"NA"},{"id":"P14-MailRu-Mail.Ru Cloud Solutions-P14.08","name":"P14.08","position":8,"score":"NA","value":"NA"},{"id":"P14-MailRu-Mail.Ru Cloud Solutions-P14.09","name":"P14.09","position":9,"score":"NA","value":"NA"},{"id":"P14-MailRu-Mail.Ru Cloud Solutions-P14.10","name":"P14.10","position":10,"score":"NA","value":"NA"},{"id":"P14-MailRu-Mail.Ru Cloud Solutions-P14.11","name":"P14.11","position":11,"score":"NA","value":"NA"}],"Mail.Ru Agent":[{"id":"P14-MailRu-Mail.Ru Agent-P14.01","name":"P14.01","position":1,"score":100,"value":"Yes"},{"id":"P14-MailRu-Mail.Ru Agent-P14.02","name":"P14.02","position":2,"score":100,"value":"Yes"},{"id":"P14-MailRu-Mail.Ru Agent-P14.03","name":"P14.03","position":3,"score":0,"value":"No Disclosure Found"},{"id":"P14-MailRu-Mail.Ru Agent-P14.04","name":"P14.04","position":4,"score":"NA","value":"NA"},{"id":"P14-MailRu-Mail.Ru Agent-P14.05","name":"P14.05","position":5,"score":"NA","value":"NA"},{"id":"P14-MailRu-Mail.Ru Agent-P14.06","name":"P14.06","position":6,"score":"NA","value":"NA"},{"id":"P14-MailRu-Mail.Ru Agent-P14.07","name":"P14.07","position":7,"score":"NA","value":"NA"},{"id":"P14-MailRu-Mail.Ru Agent-P14.08","name":"P14.08","position":8,"score":"NA","value":"NA"},{"id":"P14-MailRu-Mail.Ru Agent-P14.09","name":"P14.09","position":9,"score":"NA","value":"NA"},{"id":"P14-MailRu-Mail.Ru Agent-P14.10","name":"P14.10","position":10,"score":"NA","value":"NA"},{"id":"P14-MailRu-Mail.Ru Agent-P14.11","name":"P14.11","position":11,"score":"NA","value":"NA"}],"Mail.Ru email":[{"id":"P14-MailRu-Mail.Ru email-P14.01","name":"P14.01","position":1,"score":100,"value":"Yes"},{"id":"P14-MailRu-Mail.Ru email-P14.02","name":"P14.02","position":2,"score":100,"value":"Yes"},{"id":"P14-MailRu-Mail.Ru email-P14.03","name":"P14.03","position":3,"score":0,"value":"No Disclosure Found"},{"id":"P14-MailRu-Mail.Ru email-P14.04","name":"P14.04","position":4,"score":"NA","value":"NA"},{"id":"P14-MailRu-Mail.Ru email-P14.05","name":"P14.05","position":5,"score":"NA","value":"NA"},{"id":"P14-MailRu-Mail.Ru email-P14.06","name":"P14.06","position":6,"score":"NA","value":"NA"},{"id":"P14-MailRu-Mail.Ru email-P14.07","name":"P14.07","position":7,"score":"NA","value":"NA"},{"id":"P14-MailRu-Mail.Ru email-P14.08","name":"P14.08","position":8,"score":"NA","value":"NA"},{"id":"P14-MailRu-Mail.Ru email-P14.09","name":"P14.09","position":9,"score":"NA","value":"NA"},{"id":"P14-MailRu-Mail.Ru email-P14.10","name":"P14.10","position":10,"score":"NA","value":"NA"},{"id":"P14-MailRu-Mail.Ru email-P14.11","name":"P14.11","position":11,"score":"NA","value":"NA"}],"VKontakte":[{"id":"P14-MailRu-VKontakte-P14.01","name":"P14.01","position":1,"score":100,"value":"Yes"},{"id":"P14-MailRu-VKontakte-P14.02","name":"P14.02","position":2,"score":0,"value":"No Disclosure Found"},{"id":"P14-MailRu-VKontakte-P14.03","name":"P14.03","position":3,"score":0,"value":"No Disclosure Found"},{"id":"P14-MailRu-VKontakte-P14.04","name":"P14.04","position":4,"score":"NA","value":"NA"},{"id":"P14-MailRu-VKontakte-P14.05","name":"P14.05","position":5,"score":"NA","value":"NA"},{"id":"P14-MailRu-VKontakte-P14.06","name":"P14.06","position":6,"score":"NA","value":"NA"},{"id":"P14-MailRu-VKontakte-P14.07","name":"P14.07","position":7,"score":"NA","value":"NA"},{"id":"P14-MailRu-VKontakte-P14.08","name":"P14.08","position":8,"score":"NA","value":"NA"},{"id":"P14-MailRu-VKontakte-P14.09","name":"P14.09","position":9,"score":"NA","value":"NA"},{"id":"P14-MailRu-VKontakte-P14.10","name":"P14.10","position":10,"score":"NA","value":"NA"},{"id":"P14-MailRu-VKontakte-P14.11","name":"P14.11","position":11,"score":"NA","value":"NA"}]},"Kakao":{"KakaoTalk":[{"id":"P14-Kakao-KakaoTalk-P14.01","name":"P14.01","position":1,"score":50,"value":"Partial"},{"id":"P14-Kakao-KakaoTalk-P14.02","name":"P14.02","position":2,"score":0,"value":"No Disclosure Found"},{"id":"P14-Kakao-KakaoTalk-P14.03","name":"P14.03","position":3,"score":0,"value":"No Disclosure Found"},{"id":"P14-Kakao-KakaoTalk-P14.04","name":"P14.04","position":4,"score":"NA","value":"NA"},{"id":"P14-Kakao-KakaoTalk-P14.05","name":"P14.05","position":5,"score":"NA","value":"NA"},{"id":"P14-Kakao-KakaoTalk-P14.06","name":"P14.06","position":6,"score":"NA","value":"NA"},{"id":"P14-Kakao-KakaoTalk-P14.07","name":"P14.07","position":7,"score":"NA","value":"NA"},{"id":"P14-Kakao-KakaoTalk-P14.08","name":"P14.08","position":8,"score":"NA","value":"NA"},{"id":"P14-Kakao-KakaoTalk-P14.09","name":"P14.09","position":9,"score":"NA","value":"NA"},{"id":"P14-Kakao-KakaoTalk-P14.10","name":"P14.10","position":10,"score":"NA","value":"NA"},{"id":"P14-Kakao-KakaoTalk-P14.11","name":"P14.11","position":11,"score":"NA","value":"NA"}],"Daum Mail":[{"id":"P14-Kakao-Daum Mail-P14.01","name":"P14.01","position":1,"score":50,"value":"Partial"},{"id":"P14-Kakao-Daum Mail-P14.02","name":"P14.02","position":2,"score":0,"value":"No Disclosure Found"},{"id":"P14-Kakao-Daum Mail-P14.03","name":"P14.03","position":3,"score":0,"value":"No Disclosure Found"},{"id":"P14-Kakao-Daum Mail-P14.04","name":"P14.04","position":4,"score":"NA","value":"NA"},{"id":"P14-Kakao-Daum Mail-P14.05","name":"P14.05","position":5,"score":"NA","value":"NA"},{"id":"P14-Kakao-Daum Mail-P14.06","name":"P14.06","position":6,"score":"NA","value":"NA"},{"id":"P14-Kakao-Daum Mail-P14.07","name":"P14.07","position":7,"score":"NA","value":"NA"},{"id":"P14-Kakao-Daum Mail-P14.08","name":"P14.08","position":8,"score":"NA","value":"NA"},{"id":"P14-Kakao-Daum Mail-P14.09","name":"P14.09","position":9,"score":"NA","value":"NA"},{"id":"P14-Kakao-Daum Mail-P14.10","name":"P14.10","position":10,"score":"NA","value":"NA"},{"id":"P14-Kakao-Daum Mail-P14.11","name":"P14.11","position":11,"score":"NA","value":"NA"}],"Daum Search":[{"id":"P14-Kakao-Daum Search-P14.01","name":"P14.01","position":1,"score":50,"value":"Partial"},{"id":"P14-Kakao-Daum Search-P14.02","name":"P14.02","position":2,"score":0,"value":"No Disclosure Found"},{"id":"P14-Kakao-Daum Search-P14.03","name":"P14.03","position":3,"score":0,"value":"No Disclosure Found"},{"id":"P14-Kakao-Daum Search-P14.04","name":"P14.04","position":4,"score":"NA","value":"NA"},{"id":"P14-Kakao-Daum Search-P14.05","name":"P14.05","position":5,"score":"NA","value":"NA"},{"id":"P14-Kakao-Daum Search-P14.06","name":"P14.06","position":6,"score":"NA","value":"NA"},{"id":"P14-Kakao-Daum Search-P14.07","name":"P14.07","position":7,"score":"NA","value":"NA"},{"id":"P14-Kakao-Daum Search-P14.08","name":"P14.08","position":8,"score":"NA","value":"NA"},{"id":"P14-Kakao-Daum Search-P14.09","name":"P14.09","position":9,"score":"NA","value":"NA"},{"id":"P14-Kakao-Daum Search-P14.10","name":"P14.10","position":10,"score":"NA","value":"NA"},{"id":"P14-Kakao-Daum Search-P14.11","name":"P14.11","position":11,"score":"NA","value":"NA"}]},"Google":{"Google Drive":[{"id":"P14-Google-Google Drive-P14.01","name":"P14.01","position":1,"score":100,"value":"Yes"},{"id":"P14-Google-Google Drive-P14.02","name":"P14.02","position":2,"score":0,"value":"No Disclosure Found"},{"id":"P14-Google-Google Drive-P14.03","name":"P14.03","position":3,"score":0,"value":"No Disclosure Found"},{"id":"P14-Google-Google Drive-P14.04","name":"P14.04","position":4,"score":"NA","value":"NA"},{"id":"P14-Google-Google Drive-P14.05","name":"P14.05","position":5,"score":"NA","value":"NA"},{"id":"P14-Google-Google Drive-P14.06","name":"P14.06","position":6,"score":"NA","value":"NA"},{"id":"P14-Google-Google Drive-P14.07","name":"P14.07","position":7,"score":"NA","value":"NA"},{"id":"P14-Google-Google Drive-P14.08","name":"P14.08","position":8,"score":"NA","value":"NA"},{"id":"P14-Google-Google Drive-P14.09","name":"P14.09","position":9,"score":"NA","value":"NA"},{"id":"P14-Google-Google Drive-P14.10","name":"P14.10","position":10,"score":"NA","value":"NA"},{"id":"P14-Google-Google Drive-P14.11","name":"P14.11","position":11,"score":"NA","value":"NA"}],"Android mobile ecosystem":[{"id":"P14-Google-Android mobile ecosystem-P14.01","name":"P14.01","position":1,"score":100,"value":"Yes"},{"id":"P14-Google-Android mobile ecosystem-P14.02","name":"P14.02","position":2,"score":50,"value":"Partial"},{"id":"P14-Google-Android mobile ecosystem-P14.03","name":"P14.03","position":3,"score":0,"value":"No Disclosure Found"},{"id":"P14-Google-Android mobile ecosystem-P14.04","name":"P14.04","position":4,"score":0,"value":"No Disclosure Found"},{"id":"P14-Google-Android mobile ecosystem-P14.05","name":"P14.05","position":5,"score":"NA","value":"NA"},{"id":"P14-Google-Android mobile ecosystem-P14.06","name":"P14.06","position":6,"score":"NA","value":"NA"},{"id":"P14-Google-Android mobile ecosystem-P14.07","name":"P14.07","position":7,"score":100,"value":"Yes"},{"id":"P14-Google-Android mobile ecosystem-P14.08","name":"P14.08","position":8,"score":0,"value":"No"},{"id":"P14-Google-Android mobile ecosystem-P14.09","name":"P14.09","position":9,"score":"NA","value":"NA"},{"id":"P14-Google-Android mobile ecosystem-P14.10","name":"P14.10","position":10,"score":"NA","value":"NA"},{"id":"P14-Google-Android mobile ecosystem-P14.11","name":"P14.11","position":11,"score":"NA","value":"NA"}],"YouTube":[{"id":"P14-Google-YouTube-P14.01","name":"P14.01","position":1,"score":100,"value":"Yes"},{"id":"P14-Google-YouTube-P14.02","name":"P14.02","position":2,"score":0,"value":"No Disclosure Found"},{"id":"P14-Google-YouTube-P14.03","name":"P14.03","position":3,"score":0,"value":"No Disclosure Found"},{"id":"P14-Google-YouTube-P14.04","name":"P14.04","position":4,"score":"NA","value":"NA"},{"id":"P14-Google-YouTube-P14.05","name":"P14.05","position":5,"score":"NA","value":"NA"},{"id":"P14-Google-YouTube-P14.06","name":"P14.06","position":6,"score":"NA","value":"NA"},{"id":"P14-Google-YouTube-P14.07","name":"P14.07","position":7,"score":"NA","value":"NA"},{"id":"P14-Google-YouTube-P14.08","name":"P14.08","position":8,"score":"NA","value":"NA"},{"id":"P14-Google-YouTube-P14.09","name":"P14.09","position":9,"score":"NA","value":"NA"},{"id":"P14-Google-YouTube-P14.10","name":"P14.10","position":10,"score":"NA","value":"NA"},{"id":"P14-Google-YouTube-P14.11","name":"P14.11","position":11,"score":"NA","value":"NA"}],"Gmail":[{"id":"P14-Google-Gmail-P14.01","name":"P14.01","position":1,"score":100,"value":"Yes"},{"id":"P14-Google-Gmail-P14.02","name":"P14.02","position":2,"score":0,"value":"No Disclosure Found"},{"id":"P14-Google-Gmail-P14.03","name":"P14.03","position":3,"score":0,"value":"No Disclosure Found"},{"id":"P14-Google-Gmail-P14.04","name":"P14.04","position":4,"score":"NA","value":"NA"},{"id":"P14-Google-Gmail-P14.05","name":"P14.05","position":5,"score":"NA","value":"NA"},{"id":"P14-Google-Gmail-P14.06","name":"P14.06","position":6,"score":"NA","value":"NA"},{"id":"P14-Google-Gmail-P14.07","name":"P14.07","position":7,"score":"NA","value":"NA"},{"id":"P14-Google-Gmail-P14.08","name":"P14.08","position":8,"score":"NA","value":"NA"},{"id":"P14-Google-Gmail-P14.09","name":"P14.09","position":9,"score":"NA","value":"NA"},{"id":"P14-Google-Gmail-P14.10","name":"P14.10","position":10,"score":"NA","value":"NA"},{"id":"P14-Google-Gmail-P14.11","name":"P14.11","position":11,"score":"NA","value":"NA"}],"Google Search":[{"id":"P14-Google-Google Search-P14.01","name":"P14.01","position":1,"score":100,"value":"Yes"},{"id":"P14-Google-Google Search-P14.02","name":"P14.02","position":2,"score":0,"value":"No Disclosure Found"},{"id":"P14-Google-Google Search-P14.03","name":"P14.03","position":3,"score":0,"value":"No Disclosure Found"},{"id":"P14-Google-Google Search-P14.04","name":"P14.04","position":4,"score":"NA","value":"NA"},{"id":"P14-Google-Google Search-P14.05","name":"P14.05","position":5,"score":"NA","value":"NA"},{"id":"P14-Google-Google Search-P14.06","name":"P14.06","position":6,"score":"NA","value":"NA"},{"id":"P14-Google-Google Search-P14.07","name":"P14.07","position":7,"score":"NA","value":"NA"},{"id":"P14-Google-Google Search-P14.08","name":"P14.08","position":8,"score":"NA","value":"NA"},{"id":"P14-Google-Google Search-P14.09","name":"P14.09","position":9,"score":"NA","value":"NA"},{"id":"P14-Google-Google Search-P14.10","name":"P14.10","position":10,"score":"NA","value":"NA"},{"id":"P14-Google-Google Search-P14.11","name":"P14.11","position":11,"score":"NA","value":"NA"}]},"Facebook":{"Messenger":[{"id":"P14-Facebook-Messenger-P14.01","name":"P14.01","position":1,"score":100,"value":"Yes"},{"id":"P14-Facebook-Messenger-P14.02","name":"P14.02","position":2,"score":0,"value":"No Disclosure Found"},{"id":"P14-Facebook-Messenger-P14.03","name":"P14.03","position":3,"score":100,"value":"Yes"},{"id":"P14-Facebook-Messenger-P14.04","name":"P14.04","position":4,"score":"NA","value":"NA"},{"id":"P14-Facebook-Messenger-P14.05","name":"P14.05","position":5,"score":"NA","value":"NA"},{"id":"P14-Facebook-Messenger-P14.06","name":"P14.06","position":6,"score":"NA","value":"NA"},{"id":"P14-Facebook-Messenger-P14.07","name":"P14.07","position":7,"score":"NA","value":"NA"},{"id":"P14-Facebook-Messenger-P14.08","name":"P14.08","position":8,"score":"NA","value":"NA"},{"id":"P14-Facebook-Messenger-P14.09","name":"P14.09","position":9,"score":"NA","value":"NA"},{"id":"P14-Facebook-Messenger-P14.10","name":"P14.10","position":10,"score":"NA","value":"NA"},{"id":"P14-Facebook-Messenger-P14.11","name":"P14.11","position":11,"score":"NA","value":"NA"}],"WhatsApp":[{"id":"P14-Facebook-WhatsApp-P14.01","name":"P14.01","position":1,"score":100,"value":"Yes"},{"id":"P14-Facebook-WhatsApp-P14.02","name":"P14.02","position":2,"score":0,"value":"No Disclosure Found"},{"id":"P14-Facebook-WhatsApp-P14.03","name":"P14.03","position":3,"score":100,"value":"Yes"},{"id":"P14-Facebook-WhatsApp-P14.04","name":"P14.04","position":4,"score":"NA","value":"NA"},{"id":"P14-Facebook-WhatsApp-P14.05","name":"P14.05","position":5,"score":"NA","value":"NA"},{"id":"P14-Facebook-WhatsApp-P14.06","name":"P14.06","position":6,"score":"NA","value":"NA"},{"id":"P14-Facebook-WhatsApp-P14.07","name":"P14.07","position":7,"score":"NA","value":"NA"},{"id":"P14-Facebook-WhatsApp-P14.08","name":"P14.08","position":8,"score":"NA","value":"NA"},{"id":"P14-Facebook-WhatsApp-P14.09","name":"P14.09","position":9,"score":"NA","value":"NA"},{"id":"P14-Facebook-WhatsApp-P14.10","name":"P14.10","position":10,"score":"NA","value":"NA"},{"id":"P14-Facebook-WhatsApp-P14.11","name":"P14.11","position":11,"score":"NA","value":"NA"}],"Instagram":[{"id":"P14-Facebook-Instagram-P14.01","name":"P14.01","position":1,"score":100,"value":"Yes"},{"id":"P14-Facebook-Instagram-P14.02","name":"P14.02","position":2,"score":0,"value":"No Disclosure Found"},{"id":"P14-Facebook-Instagram-P14.03","name":"P14.03","position":3,"score":100,"value":"Yes"},{"id":"P14-Facebook-Instagram-P14.04","name":"P14.04","position":4,"score":"NA","value":"NA"},{"id":"P14-Facebook-Instagram-P14.05","name":"P14.05","position":5,"score":"NA","value":"NA"},{"id":"P14-Facebook-Instagram-P14.06","name":"P14.06","position":6,"score":"NA","value":"NA"},{"id":"P14-Facebook-Instagram-P14.07","name":"P14.07","position":7,"score":"NA","value":"NA"},{"id":"P14-Facebook-Instagram-P14.08","name":"P14.08","position":8,"score":"NA","value":"NA"},{"id":"P14-Facebook-Instagram-P14.09","name":"P14.09","position":9,"score":"NA","value":"NA"},{"id":"P14-Facebook-Instagram-P14.10","name":"P14.10","position":10,"score":"NA","value":"NA"},{"id":"P14-Facebook-Instagram-P14.11","name":"P14.11","position":11,"score":"NA","value":"NA"}],"Facebook":[{"id":"P14-Facebook-Facebook-P14.01","name":"P14.01","position":1,"score":100,"value":"Yes"},{"id":"P14-Facebook-Facebook-P14.02","name":"P14.02","position":2,"score":0,"value":"No Disclosure Found"},{"id":"P14-Facebook-Facebook-P14.03","name":"P14.03","position":3,"score":100,"value":"Yes"},{"id":"P14-Facebook-Facebook-P14.04","name":"P14.04","position":4,"score":"NA","value":"NA"},{"id":"P14-Facebook-Facebook-P14.05","name":"P14.05","position":5,"score":"NA","value":"NA"},{"id":"P14-Facebook-Facebook-P14.06","name":"P14.06","position":6,"score":"NA","value":"NA"},{"id":"P14-Facebook-Facebook-P14.07","name":"P14.07","position":7,"score":"NA","value":"NA"},{"id":"P14-Facebook-Facebook-P14.08","name":"P14.08","position":8,"score":"NA","value":"NA"},{"id":"P14-Facebook-Facebook-P14.09","name":"P14.09","position":9,"score":"NA","value":"NA"},{"id":"P14-Facebook-Facebook-P14.10","name":"P14.10","position":10,"score":"NA","value":"NA"},{"id":"P14-Facebook-Facebook-P14.11","name":"P14.11","position":11,"score":"NA","value":"NA"}]},"Etisalat":{"Fixed-line broadband":[{"id":"P14-Etisalat-Fixed-line broadband-P14.01","name":"P14.01","position":1,"score":0,"value":"No Disclosure Found"},{"id":"P14-Etisalat-Fixed-line broadband-P14.02","name":"P14.02","position":2,"score":0,"value":"No Disclosure Found"},{"id":"P14-Etisalat-Fixed-line broadband-P14.03","name":"P14.03","position":3,"score":0,"value":"No Disclosure Found"},{"id":"P14-Etisalat-Fixed-line broadband-P14.04","name":"P14.04","position":4,"score":"NA","value":"NA"},{"id":"P14-Etisalat-Fixed-line broadband-P14.05","name":"P14.05","position":5,"score":"NA","value":"NA"},{"id":"P14-Etisalat-Fixed-line broadband-P14.06","name":"P14.06","position":6,"score":"NA","value":"NA"},{"id":"P14-Etisalat-Fixed-line broadband-P14.07","name":"P14.07","position":7,"score":"NA","value":"NA"},{"id":"P14-Etisalat-Fixed-line broadband-P14.08","name":"P14.08","position":8,"score":"NA","value":"NA"},{"id":"P14-Etisalat-Fixed-line broadband-P14.09","name":"P14.09","position":9,"score":"NA","value":"NA"},{"id":"P14-Etisalat-Fixed-line broadband-P14.10","name":"P14.10","position":10,"score":"NA","value":"NA"},{"id":"P14-Etisalat-Fixed-line broadband-P14.11","name":"P14.11","position":11,"score":"NA","value":"NA"}],"Postpaid mobile":[{"id":"P14-Etisalat-Postpaid mobile-P14.01","name":"P14.01","position":1,"score":0,"value":"No Disclosure Found"},{"id":"P14-Etisalat-Postpaid mobile-P14.02","name":"P14.02","position":2,"score":0,"value":"No Disclosure Found"},{"id":"P14-Etisalat-Postpaid mobile-P14.03","name":"P14.03","position":3,"score":0,"value":"No Disclosure Found"},{"id":"P14-Etisalat-Postpaid mobile-P14.04","name":"P14.04","position":4,"score":"NA","value":"NA"},{"id":"P14-Etisalat-Postpaid mobile-P14.05","name":"P14.05","position":5,"score":0,"value":"No Disclosure Found"},{"id":"P14-Etisalat-Postpaid mobile-P14.06","name":"P14.06","position":6,"score":0,"value":"No Disclosure Found"},{"id":"P14-Etisalat-Postpaid mobile-P14.07","name":"P14.07","position":7,"score":"NA","value":"NA"},{"id":"P14-Etisalat-Postpaid mobile-P14.08","name":"P14.08","position":8,"score":"NA","value":"NA"},{"id":"P14-Etisalat-Postpaid mobile-P14.09","name":"P14.09","position":9,"score":0,"value":"No Disclosure Found"},{"id":"P14-Etisalat-Postpaid mobile-P14.10","name":"P14.10","position":10,"score":"NA","value":"NA"},{"id":"P14-Etisalat-Postpaid mobile-P14.11","name":"P14.11","position":11,"score":"NA","value":"NA"}],"Prepaid mobile":[{"id":"P14-Etisalat-Prepaid mobile-P14.01","name":"P14.01","position":1,"score":0,"value":"No Disclosure Found"},{"id":"P14-Etisalat-Prepaid mobile-P14.02","name":"P14.02","position":2,"score":0,"value":"No Disclosure Found"},{"id":"P14-Etisalat-Prepaid mobile-P14.03","name":"P14.03","position":3,"score":0,"value":"No Disclosure Found"},{"id":"P14-Etisalat-Prepaid mobile-P14.04","name":"P14.04","position":4,"score":"NA","value":"NA"},{"id":"P14-Etisalat-Prepaid mobile-P14.05","name":"P14.05","position":5,"score":0,"value":"No Disclosure Found"},{"id":"P14-Etisalat-Prepaid mobile-P14.06","name":"P14.06","position":6,"score":0,"value":"No Disclosure Found"},{"id":"P14-Etisalat-Prepaid mobile-P14.07","name":"P14.07","position":7,"score":"NA","value":"NA"},{"id":"P14-Etisalat-Prepaid mobile-P14.08","name":"P14.08","position":8,"score":"NA","value":"NA"},{"id":"P14-Etisalat-Prepaid mobile-P14.09","name":"P14.09","position":9,"score":0,"value":"No Disclosure Found"},{"id":"P14-Etisalat-Prepaid mobile-P14.10","name":"P14.10","position":10,"score":"NA","value":"NA"},{"id":"P14-Etisalat-Prepaid mobile-P14.11","name":"P14.11","position":11,"score":"NA","value":"NA"}]},"DeutscheTelekom":{"Fixed-line broadband":[{"id":"P14-DeutscheTelekom-Fixed-line broadband-P14.01","name":"P14.01","position":1,"score":50,"value":"Partial"},{"id":"P14-DeutscheTelekom-Fixed-line broadband-P14.02","name":"P14.02","position":2,"score":0,"value":"No Disclosure Found"},{"id":"P14-DeutscheTelekom-Fixed-line broadband-P14.03","name":"P14.03","position":3,"score":0,"value":"No Disclosure Found"},{"id":"P14-DeutscheTelekom-Fixed-line broadband-P14.04","name":"P14.04","position":4,"score":"NA","value":"NA"},{"id":"P14-DeutscheTelekom-Fixed-line broadband-P14.05","name":"P14.05","position":5,"score":0,"value":"No Disclosure Found"},{"id":"P14-DeutscheTelekom-Fixed-line broadband-P14.06","name":"P14.06","position":6,"score":0,"value":"No Disclosure Found"},{"id":"P14-DeutscheTelekom-Fixed-line broadband-P14.07","name":"P14.07","position":7,"score":"NA","value":"NA"},{"id":"P14-DeutscheTelekom-Fixed-line broadband-P14.08","name":"P14.08","position":8,"score":"NA","value":"NA"},{"id":"P14-DeutscheTelekom-Fixed-line broadband-P14.09","name":"P14.09","position":9,"score":0,"value":"No Disclosure Found"},{"id":"P14-DeutscheTelekom-Fixed-line broadband-P14.10","name":"P14.10","position":10,"score":"NA","value":"NA"},{"id":"P14-DeutscheTelekom-Fixed-line broadband-P14.11","name":"P14.11","position":11,"score":"NA","value":"NA"}],"Postpaid mobile":[{"id":"P14-DeutscheTelekom-Postpaid mobile-P14.01","name":"P14.01","position":1,"score":50,"value":"Partial"},{"id":"P14-DeutscheTelekom-Postpaid mobile-P14.02","name":"P14.02","position":2,"score":0,"value":"No Disclosure Found"},{"id":"P14-DeutscheTelekom-Postpaid mobile-P14.03","name":"P14.03","position":3,"score":0,"value":"No Disclosure Found"},{"id":"P14-DeutscheTelekom-Postpaid mobile-P14.04","name":"P14.04","position":4,"score":"NA","value":"NA"},{"id":"P14-DeutscheTelekom-Postpaid mobile-P14.05","name":"P14.05","position":5,"score":0,"value":"No Disclosure Found"},{"id":"P14-DeutscheTelekom-Postpaid mobile-P14.06","name":"P14.06","position":6,"score":0,"value":"No Disclosure Found"},{"id":"P14-DeutscheTelekom-Postpaid mobile-P14.07","name":"P14.07","position":7,"score":"NA","value":"NA"},{"id":"P14-DeutscheTelekom-Postpaid mobile-P14.08","name":"P14.08","position":8,"score":"NA","value":"NA"},{"id":"P14-DeutscheTelekom-Postpaid mobile-P14.09","name":"P14.09","position":9,"score":0,"value":"No Disclosure Found"},{"id":"P14-DeutscheTelekom-Postpaid mobile-P14.10","name":"P14.10","position":10,"score":"NA","value":"NA"},{"id":"P14-DeutscheTelekom-Postpaid mobile-P14.11","name":"P14.11","position":11,"score":"NA","value":"NA"}],"Prepaid mobile":[{"id":"P14-DeutscheTelekom-Prepaid mobile-P14.01","name":"P14.01","position":1,"score":50,"value":"Partial"},{"id":"P14-DeutscheTelekom-Prepaid mobile-P14.02","name":"P14.02","position":2,"score":0,"value":"No Disclosure Found"},{"id":"P14-DeutscheTelekom-Prepaid mobile-P14.03","name":"P14.03","position":3,"score":0,"value":"No Disclosure Found"},{"id":"P14-DeutscheTelekom-Prepaid mobile-P14.04","name":"P14.04","position":4,"score":"NA","value":"NA"},{"id":"P14-DeutscheTelekom-Prepaid mobile-P14.05","name":"P14.05","position":5,"score":0,"value":"No Disclosure Found"},{"id":"P14-DeutscheTelekom-Prepaid mobile-P14.06","name":"P14.06","position":6,"score":0,"value":"No Disclosure Found"},{"id":"P14-DeutscheTelekom-Prepaid mobile-P14.07","name":"P14.07","position":7,"score":"NA","value":"NA"},{"id":"P14-DeutscheTelekom-Prepaid mobile-P14.08","name":"P14.08","position":8,"score":"NA","value":"NA"},{"id":"P14-DeutscheTelekom-Prepaid mobile-P14.09","name":"P14.09","position":9,"score":0,"value":"No Disclosure Found"},{"id":"P14-DeutscheTelekom-Prepaid mobile-P14.10","name":"P14.10","position":10,"score":"NA","value":"NA"},{"id":"P14-DeutscheTelekom-Prepaid mobile-P14.11","name":"P14.11","position":11,"score":"NA","value":"NA"}]},"BhartiAirtel":{"Fixed-line broadband":[{"id":"P14-BhartiAirtel-Fixed-line broadband-P14.01","name":"P14.01","position":1,"score":0,"value":"No Disclosure Found"},{"id":"P14-BhartiAirtel-Fixed-line broadband-P14.02","name":"P14.02","position":2,"score":0,"value":"No Disclosure Found"},{"id":"P14-BhartiAirtel-Fixed-line broadband-P14.03","name":"P14.03","position":3,"score":0,"value":"No Disclosure Found"},{"id":"P14-BhartiAirtel-Fixed-line broadband-P14.04","name":"P14.04","position":4,"score":"NA","value":"NA"},{"id":"P14-BhartiAirtel-Fixed-line broadband-P14.05","name":"P14.05","position":5,"score":"NA","value":"NA"},{"id":"P14-BhartiAirtel-Fixed-line broadband-P14.06","name":"P14.06","position":6,"score":"NA","value":"NA"},{"id":"P14-BhartiAirtel-Fixed-line broadband-P14.07","name":"P14.07","position":7,"score":"NA","value":"NA"},{"id":"P14-BhartiAirtel-Fixed-line broadband-P14.08","name":"P14.08","position":8,"score":"NA","value":"NA"},{"id":"P14-BhartiAirtel-Fixed-line broadband-P14.09","name":"P14.09","position":9,"score":"NA","value":"NA"},{"id":"P14-BhartiAirtel-Fixed-line broadband-P14.10","name":"P14.10","position":10,"score":"NA","value":"NA"},{"id":"P14-BhartiAirtel-Fixed-line broadband-P14.11","name":"P14.11","position":11,"score":"NA","value":"NA"}],"Postpaid mobile":[{"id":"P14-BhartiAirtel-Postpaid mobile-P14.01","name":"P14.01","position":1,"score":0,"value":"No Disclosure Found"},{"id":"P14-BhartiAirtel-Postpaid mobile-P14.02","name":"P14.02","position":2,"score":0,"value":"No Disclosure Found"},{"id":"P14-BhartiAirtel-Postpaid mobile-P14.03","name":"P14.03","position":3,"score":0,"value":"No Disclosure Found"},{"id":"P14-BhartiAirtel-Postpaid mobile-P14.04","name":"P14.04","position":4,"score":"NA","value":"NA"},{"id":"P14-BhartiAirtel-Postpaid mobile-P14.05","name":"P14.05","position":5,"score":0,"value":"No Disclosure Found"},{"id":"P14-BhartiAirtel-Postpaid mobile-P14.06","name":"P14.06","position":6,"score":0,"value":"No Disclosure Found"},{"id":"P14-BhartiAirtel-Postpaid mobile-P14.07","name":"P14.07","position":7,"score":"NA","value":"NA"},{"id":"P14-BhartiAirtel-Postpaid mobile-P14.08","name":"P14.08","position":8,"score":"NA","value":"NA"},{"id":"P14-BhartiAirtel-Postpaid mobile-P14.09","name":"P14.09","position":9,"score":0,"value":"No Disclosure Found"},{"id":"P14-BhartiAirtel-Postpaid mobile-P14.10","name":"P14.10","position":10,"score":"NA","value":"NA"},{"id":"P14-BhartiAirtel-Postpaid mobile-P14.11","name":"P14.11","position":11,"score":"NA","value":"NA"}],"Prepaid mobile":[{"id":"P14-BhartiAirtel-Prepaid mobile-P14.01","name":"P14.01","position":1,"score":0,"value":"No Disclosure Found"},{"id":"P14-BhartiAirtel-Prepaid mobile-P14.02","name":"P14.02","position":2,"score":0,"value":"No Disclosure Found"},{"id":"P14-BhartiAirtel-Prepaid mobile-P14.03","name":"P14.03","position":3,"score":0,"value":"No Disclosure Found"},{"id":"P14-BhartiAirtel-Prepaid mobile-P14.04","name":"P14.04","position":4,"score":"NA","value":"NA"},{"id":"P14-BhartiAirtel-Prepaid mobile-P14.05","name":"P14.05","position":5,"score":0,"value":"No Disclosure Found"},{"id":"P14-BhartiAirtel-Prepaid mobile-P14.06","name":"P14.06","position":6,"score":0,"value":"No Disclosure Found"},{"id":"P14-BhartiAirtel-Prepaid mobile-P14.07","name":"P14.07","position":7,"score":"NA","value":"NA"},{"id":"P14-BhartiAirtel-Prepaid mobile-P14.08","name":"P14.08","position":8,"score":"NA","value":"NA"},{"id":"P14-BhartiAirtel-Prepaid mobile-P14.09","name":"P14.09","position":9,"score":0,"value":"No Disclosure Found"},{"id":"P14-BhartiAirtel-Prepaid mobile-P14.10","name":"P14.10","position":10,"score":"NA","value":"NA"},{"id":"P14-BhartiAirtel-Prepaid mobile-P14.11","name":"P14.11","position":11,"score":"NA","value":"NA"}]},"Baidu":{"Baidu PostBar":[{"id":"P14-Baidu-Baidu PostBar-P14.01","name":"P14.01","position":1,"score":100,"value":"Yes"},{"id":"P14-Baidu-Baidu PostBar-P14.02","name":"P14.02","position":2,"score":0,"value":"No Disclosure Found"},{"id":"P14-Baidu-Baidu PostBar-P14.03","name":"P14.03","position":3,"score":0,"value":"No Disclosure Found"},{"id":"P14-Baidu-Baidu PostBar-P14.04","name":"P14.04","position":4,"score":"NA","value":"NA"},{"id":"P14-Baidu-Baidu PostBar-P14.05","name":"P14.05","position":5,"score":"NA","value":"NA"},{"id":"P14-Baidu-Baidu PostBar-P14.06","name":"P14.06","position":6,"score":"NA","value":"NA"},{"id":"P14-Baidu-Baidu PostBar-P14.07","name":"P14.07","position":7,"score":"NA","value":"NA"},{"id":"P14-Baidu-Baidu PostBar-P14.08","name":"P14.08","position":8,"score":"NA","value":"NA"},{"id":"P14-Baidu-Baidu PostBar-P14.09","name":"P14.09","position":9,"score":"NA","value":"NA"},{"id":"P14-Baidu-Baidu PostBar-P14.10","name":"P14.10","position":10,"score":"NA","value":"NA"},{"id":"P14-Baidu-Baidu PostBar-P14.11","name":"P14.11","position":11,"score":"NA","value":"NA"}],"Baidu Cloud":[{"id":"P14-Baidu-Baidu Cloud-P14.01","name":"P14.01","position":1,"score":100,"value":"Yes"},{"id":"P14-Baidu-Baidu Cloud-P14.02","name":"P14.02","position":2,"score":0,"value":"No Disclosure Found"},{"id":"P14-Baidu-Baidu Cloud-P14.03","name":"P14.03","position":3,"score":0,"value":"No Disclosure Found"},{"id":"P14-Baidu-Baidu Cloud-P14.04","name":"P14.04","position":4,"score":"NA","value":"NA"},{"id":"P14-Baidu-Baidu Cloud-P14.05","name":"P14.05","position":5,"score":"NA","value":"NA"},{"id":"P14-Baidu-Baidu Cloud-P14.06","name":"P14.06","position":6,"score":"NA","value":"NA"},{"id":"P14-Baidu-Baidu Cloud-P14.07","name":"P14.07","position":7,"score":"NA","value":"NA"},{"id":"P14-Baidu-Baidu Cloud-P14.08","name":"P14.08","position":8,"score":"NA","value":"NA"},{"id":"P14-Baidu-Baidu Cloud-P14.09","name":"P14.09","position":9,"score":"NA","value":"NA"},{"id":"P14-Baidu-Baidu Cloud-P14.10","name":"P14.10","position":10,"score":"NA","value":"NA"},{"id":"P14-Baidu-Baidu Cloud-P14.11","name":"P14.11","position":11,"score":"NA","value":"NA"}],"Baidu Search":[{"id":"P14-Baidu-Baidu Search-P14.01","name":"P14.01","position":1,"score":100,"value":"Yes"},{"id":"P14-Baidu-Baidu Search-P14.02","name":"P14.02","position":2,"score":0,"value":"No Disclosure Found"},{"id":"P14-Baidu-Baidu Search-P14.03","name":"P14.03","position":3,"score":0,"value":"No Disclosure Found"},{"id":"P14-Baidu-Baidu Search-P14.04","name":"P14.04","position":4,"score":"NA","value":"NA"},{"id":"P14-Baidu-Baidu Search-P14.05","name":"P14.05","position":5,"score":"NA","value":"NA"},{"id":"P14-Baidu-Baidu Search-P14.06","name":"P14.06","position":6,"score":"NA","value":"NA"},{"id":"P14-Baidu-Baidu Search-P14.07","name":"P14.07","position":7,"score":"NA","value":"NA"},{"id":"P14-Baidu-Baidu Search-P14.08","name":"P14.08","position":8,"score":"NA","value":"NA"},{"id":"P14-Baidu-Baidu Search-P14.09","name":"P14.09","position":9,"score":"NA","value":"NA"},{"id":"P14-Baidu-Baidu Search-P14.10","name":"P14.10","position":10,"score":"NA","value":"NA"},{"id":"P14-Baidu-Baidu Search-P14.11","name":"P14.11","position":11,"score":"NA","value":"NA"}]},"Axiata":{"Fixed-line broadband":[{"id":"P14-Axiata-Fixed-line broadband-P14.01","name":"P14.01","position":1,"score":0,"value":"No Disclosure Found"},{"id":"P14-Axiata-Fixed-line broadband-P14.02","name":"P14.02","position":2,"score":0,"value":"No Disclosure Found"},{"id":"P14-Axiata-Fixed-line broadband-P14.03","name":"P14.03","position":3,"score":0,"value":"No Disclosure Found"},{"id":"P14-Axiata-Fixed-line broadband-P14.04","name":"P14.04","position":4,"score":"NA","value":"NA"},{"id":"P14-Axiata-Fixed-line broadband-P14.05","name":"P14.05","position":5,"score":"NA","value":"NA"},{"id":"P14-Axiata-Fixed-line broadband-P14.06","name":"P14.06","position":6,"score":"NA","value":"NA"},{"id":"P14-Axiata-Fixed-line broadband-P14.07","name":"P14.07","position":7,"score":"NA","value":"NA"},{"id":"P14-Axiata-Fixed-line broadband-P14.08","name":"P14.08","position":8,"score":"NA","value":"NA"},{"id":"P14-Axiata-Fixed-line broadband-P14.09","name":"P14.09","position":9,"score":"NA","value":"NA"},{"id":"P14-Axiata-Fixed-line broadband-P14.10","name":"P14.10","position":10,"score":"NA","value":"NA"},{"id":"P14-Axiata-Fixed-line broadband-P14.11","name":"P14.11","position":11,"score":"NA","value":"NA"}],"Postpaid mobile":[{"id":"P14-Axiata-Postpaid mobile-P14.01","name":"P14.01","position":1,"score":0,"value":"No Disclosure Found"},{"id":"P14-Axiata-Postpaid mobile-P14.02","name":"P14.02","position":2,"score":0,"value":"No Disclosure Found"},{"id":"P14-Axiata-Postpaid mobile-P14.03","name":"P14.03","position":3,"score":0,"value":"No Disclosure Found"},{"id":"P14-Axiata-Postpaid mobile-P14.04","name":"P14.04","position":4,"score":"NA","value":"NA"},{"id":"P14-Axiata-Postpaid mobile-P14.05","name":"P14.05","position":5,"score":0,"value":"No Disclosure Found"},{"id":"P14-Axiata-Postpaid mobile-P14.06","name":"P14.06","position":6,"score":0,"value":"No Disclosure Found"},{"id":"P14-Axiata-Postpaid mobile-P14.07","name":"P14.07","position":7,"score":"NA","value":"NA"},{"id":"P14-Axiata-Postpaid mobile-P14.08","name":"P14.08","position":8,"score":"NA","value":"NA"},{"id":"P14-Axiata-Postpaid mobile-P14.09","name":"P14.09","position":9,"score":0,"value":"No Disclosure Found"},{"id":"P14-Axiata-Postpaid mobile-P14.10","name":"P14.10","position":10,"score":"NA","value":"NA"},{"id":"P14-Axiata-Postpaid mobile-P14.11","name":"P14.11","position":11,"score":"NA","value":"NA"}],"Prepaid mobile":[{"id":"P14-Axiata-Prepaid mobile-P14.01","name":"P14.01","position":1,"score":0,"value":"No Disclosure Found"},{"id":"P14-Axiata-Prepaid mobile-P14.02","name":"P14.02","position":2,"score":0,"value":"No Disclosure Found"},{"id":"P14-Axiata-Prepaid mobile-P14.03","name":"P14.03","position":3,"score":0,"value":"No Disclosure Found"},{"id":"P14-Axiata-Prepaid mobile-P14.04","name":"P14.04","position":4,"score":"NA","value":"NA"},{"id":"P14-Axiata-Prepaid mobile-P14.05","name":"P14.05","position":5,"score":0,"value":"No Disclosure Found"},{"id":"P14-Axiata-Prepaid mobile-P14.06","name":"P14.06","position":6,"score":0,"value":"No Disclosure Found"},{"id":"P14-Axiata-Prepaid mobile-P14.07","name":"P14.07","position":7,"score":"NA","value":"NA"},{"id":"P14-Axiata-Prepaid mobile-P14.08","name":"P14.08","position":8,"score":"NA","value":"NA"},{"id":"P14-Axiata-Prepaid mobile-P14.09","name":"P14.09","position":9,"score":0,"value":"No Disclosure Found"},{"id":"P14-Axiata-Prepaid mobile-P14.10","name":"P14.10","position":10,"score":"NA","value":"NA"},{"id":"P14-Axiata-Prepaid mobile-P14.11","name":"P14.11","position":11,"score":"NA","value":"NA"}]},"ATT":{"Fixed-line broadband":[{"id":"P14-ATT-Fixed-line broadband-P14.01","name":"P14.01","position":1,"score":100,"value":"Yes"},{"id":"P14-ATT-Fixed-line broadband-P14.02","name":"P14.02","position":2,"score":0,"value":"No"},{"id":"P14-ATT-Fixed-line broadband-P14.03","name":"P14.03","position":3,"score":0,"value":"No Disclosure Found"},{"id":"P14-ATT-Fixed-line broadband-P14.04","name":"P14.04","position":4,"score":"NA","value":"NA"},{"id":"P14-ATT-Fixed-line broadband-P14.05","name":"P14.05","position":5,"score":"NA","value":"NA"},{"id":"P14-ATT-Fixed-line broadband-P14.06","name":"P14.06","position":6,"score":"NA","value":"NA"},{"id":"P14-ATT-Fixed-line broadband-P14.07","name":"P14.07","position":7,"score":"NA","value":"NA"},{"id":"P14-ATT-Fixed-line broadband-P14.08","name":"P14.08","position":8,"score":"NA","value":"NA"},{"id":"P14-ATT-Fixed-line broadband-P14.09","name":"P14.09","position":9,"score":"NA","value":"NA"},{"id":"P14-ATT-Fixed-line broadband-P14.10","name":"P14.10","position":10,"score":"NA","value":"NA"},{"id":"P14-ATT-Fixed-line broadband-P14.11","name":"P14.11","position":11,"score":"NA","value":"NA"}],"Postpaid mobile":[{"id":"P14-ATT-Postpaid mobile-P14.01","name":"P14.01","position":1,"score":100,"value":"Yes"},{"id":"P14-ATT-Postpaid mobile-P14.02","name":"P14.02","position":2,"score":0,"value":"No"},{"id":"P14-ATT-Postpaid mobile-P14.03","name":"P14.03","position":3,"score":0,"value":"No Disclosure Found"},{"id":"P14-ATT-Postpaid mobile-P14.04","name":"P14.04","position":4,"score":"NA","value":"NA"},{"id":"P14-ATT-Postpaid mobile-P14.05","name":"P14.05","position":5,"score":0,"value":"No Disclosure Found"},{"id":"P14-ATT-Postpaid mobile-P14.06","name":"P14.06","position":6,"score":0,"value":"No Disclosure Found"},{"id":"P14-ATT-Postpaid mobile-P14.07","name":"P14.07","position":7,"score":"NA","value":"NA"},{"id":"P14-ATT-Postpaid mobile-P14.08","name":"P14.08","position":8,"score":"NA","value":"NA"},{"id":"P14-ATT-Postpaid mobile-P14.09","name":"P14.09","position":9,"score":0,"value":"No Disclosure Found"},{"id":"P14-ATT-Postpaid mobile-P14.10","name":"P14.10","position":10,"score":"NA","value":"NA"},{"id":"P14-ATT-Postpaid mobile-P14.11","name":"P14.11","position":11,"score":"NA","value":"NA"}],"Prepaid mobile":[{"id":"P14-ATT-Prepaid mobile-P14.01","name":"P14.01","position":1,"score":100,"value":"Yes"},{"id":"P14-ATT-Prepaid mobile-P14.02","name":"P14.02","position":2,"score":0,"value":"No"},{"id":"P14-ATT-Prepaid mobile-P14.03","name":"P14.03","position":3,"score":0,"value":"No Disclosure Found"},{"id":"P14-ATT-Prepaid mobile-P14.04","name":"P14.04","position":4,"score":"NA","value":"NA"},{"id":"P14-ATT-Prepaid mobile-P14.05","name":"P14.05","position":5,"score":0,"value":"No Disclosure Found"},{"id":"P14-ATT-Prepaid mobile-P14.06","name":"P14.06","position":6,"score":0,"value":"No Disclosure Found"},{"id":"P14-ATT-Prepaid mobile-P14.07","name":"P14.07","position":7,"score":"NA","value":"NA"},{"id":"P14-ATT-Prepaid mobile-P14.08","name":"P14.08","position":8,"score":"NA","value":"NA"},{"id":"P14-ATT-Prepaid mobile-P14.09","name":"P14.09","position":9,"score":0,"value":"No Disclosure Found"},{"id":"P14-ATT-Prepaid mobile-P14.10","name":"P14.10","position":10,"score":"NA","value":"NA"},{"id":"P14-ATT-Prepaid mobile-P14.11","name":"P14.11","position":11,"score":"NA","value":"NA"}]},"Apple":{"iCloud":[{"id":"P14-Apple-iCloud-P14.01","name":"P14.01","position":1,"score":100,"value":"Yes"},{"id":"P14-Apple-iCloud-P14.02","name":"P14.02","position":2,"score":0,"value":"No Disclosure Found"},{"id":"P14-Apple-iCloud-P14.03","name":"P14.03","position":3,"score":0,"value":"No Disclosure Found"},{"id":"P14-Apple-iCloud-P14.04","name":"P14.04","position":4,"score":"NA","value":"NA"},{"id":"P14-Apple-iCloud-P14.05","name":"P14.05","position":5,"score":"NA","value":"NA"},{"id":"P14-Apple-iCloud-P14.06","name":"P14.06","position":6,"score":"NA","value":"NA"},{"id":"P14-Apple-iCloud-P14.07","name":"P14.07","position":7,"score":"NA","value":"NA"},{"id":"P14-Apple-iCloud-P14.08","name":"P14.08","position":8,"score":"NA","value":"NA"},{"id":"P14-Apple-iCloud-P14.09","name":"P14.09","position":9,"score":"NA","value":"NA"},{"id":"P14-Apple-iCloud-P14.10","name":"P14.10","position":10,"score":"NA","value":"NA"},{"id":"P14-Apple-iCloud-P14.11","name":"P14.11","position":11,"score":"NA","value":"NA"}],"iMessage":[{"id":"P14-Apple-iMessage-P14.01","name":"P14.01","position":1,"score":100,"value":"Yes"},{"id":"P14-Apple-iMessage-P14.02","name":"P14.02","position":2,"score":0,"value":"No Disclosure Found"},{"id":"P14-Apple-iMessage-P14.03","name":"P14.03","position":3,"score":0,"value":"No Disclosure Found"},{"id":"P14-Apple-iMessage-P14.04","name":"P14.04","position":4,"score":"NA","value":"NA"},{"id":"P14-Apple-iMessage-P14.05","name":"P14.05","position":5,"score":"NA","value":"NA"},{"id":"P14-Apple-iMessage-P14.06","name":"P14.06","position":6,"score":"NA","value":"NA"},{"id":"P14-Apple-iMessage-P14.07","name":"P14.07","position":7,"score":"NA","value":"NA"},{"id":"P14-Apple-iMessage-P14.08","name":"P14.08","position":8,"score":"NA","value":"NA"},{"id":"P14-Apple-iMessage-P14.09","name":"P14.09","position":9,"score":"NA","value":"NA"},{"id":"P14-Apple-iMessage-P14.10","name":"P14.10","position":10,"score":"NA","value":"NA"},{"id":"P14-Apple-iMessage-P14.11","name":"P14.11","position":11,"score":"NA","value":"NA"}],"iOS (mobile ecosystem)":[{"id":"P14-Apple-iOS (mobile ecosystem)-P14.01","name":"P14.01","position":1,"score":100,"value":"Yes"},{"id":"P14-Apple-iOS (mobile ecosystem)-P14.02","name":"P14.02","position":2,"score":0,"value":"No Disclosure Found"},{"id":"P14-Apple-iOS (mobile ecosystem)-P14.03","name":"P14.03","position":3,"score":0,"value":"No Disclosure Found"},{"id":"P14-Apple-iOS (mobile ecosystem)-P14.04","name":"P14.04","position":4,"score":0,"value":"No Disclosure Found"},{"id":"P14-Apple-iOS (mobile ecosystem)-P14.05","name":"P14.05","position":5,"score":"NA","value":"NA"},{"id":"P14-Apple-iOS (mobile ecosystem)-P14.06","name":"P14.06","position":6,"score":"NA","value":"NA"},{"id":"P14-Apple-iOS (mobile ecosystem)-P14.07","name":"P14.07","position":7,"score":0,"value":"No Disclosure Found"},{"id":"P14-Apple-iOS (mobile ecosystem)-P14.08","name":"P14.08","position":8,"score":0,"value":"No Disclosure Found"},{"id":"P14-Apple-iOS (mobile ecosystem)-P14.09","name":"P14.09","position":9,"score":"NA","value":"NA"},{"id":"P14-Apple-iOS (mobile ecosystem)-P14.10","name":"P14.10","position":10,"score":"NA","value":"NA"},{"id":"P14-Apple-iOS (mobile ecosystem)-P14.11","name":"P14.11","position":11,"score":"NA","value":"NA"}]},"AmericaMovil":{"Postpaid mobile":[{"id":"P14-AmericaMovil-Postpaid mobile-P14.01","name":"P14.01","position":1,"score":0,"value":"No Disclosure Found"},{"id":"P14-AmericaMovil-Postpaid mobile-P14.02","name":"P14.02","position":2,"score":0,"value":"No Disclosure Found"},{"id":"P14-AmericaMovil-Postpaid mobile-P14.03","name":"P14.03","position":3,"score":0,"value":"No Disclosure Found"},{"id":"P14-AmericaMovil-Postpaid mobile-P14.04","name":"P14.04","position":4,"score":"NA","value":"NA"},{"id":"P14-AmericaMovil-Postpaid mobile-P14.05","name":"P14.05","position":5,"score":0,"value":"No Disclosure Found"},{"id":"P14-AmericaMovil-Postpaid mobile-P14.06","name":"P14.06","position":6,"score":0,"value":"No Disclosure Found"},{"id":"P14-AmericaMovil-Postpaid mobile-P14.07","name":"P14.07","position":7,"score":"NA","value":"NA"},{"id":"P14-AmericaMovil-Postpaid mobile-P14.08","name":"P14.08","position":8,"score":"NA","value":"NA"},{"id":"P14-AmericaMovil-Postpaid mobile-P14.09","name":"P14.09","position":9,"score":0,"value":"No Disclosure Found"},{"id":"P14-AmericaMovil-Postpaid mobile-P14.10","name":"P14.10","position":10,"score":"NA","value":"NA"},{"id":"P14-AmericaMovil-Postpaid mobile-P14.11","name":"P14.11","position":11,"score":"NA","value":"NA"}],"Prepaid mobile":[{"id":"P14-AmericaMovil-Prepaid mobile-P14.01","name":"P14.01","position":1,"score":0,"value":"No Disclosure Found"},{"id":"P14-AmericaMovil-Prepaid mobile-P14.02","name":"P14.02","position":2,"score":0,"value":"No Disclosure Found"},{"id":"P14-AmericaMovil-Prepaid mobile-P14.03","name":"P14.03","position":3,"score":0,"value":"No Disclosure Found"},{"id":"P14-AmericaMovil-Prepaid mobile-P14.04","name":"P14.04","position":4,"score":"NA","value":"NA"},{"id":"P14-AmericaMovil-Prepaid mobile-P14.05","name":"P14.05","position":5,"score":0,"value":"No Disclosure Found"},{"id":"P14-AmericaMovil-Prepaid mobile-P14.06","name":"P14.06","position":6,"score":0,"value":"No Disclosure Found"},{"id":"P14-AmericaMovil-Prepaid mobile-P14.07","name":"P14.07","position":7,"score":"NA","value":"NA"},{"id":"P14-AmericaMovil-Prepaid mobile-P14.08","name":"P14.08","position":8,"score":"NA","value":"NA"},{"id":"P14-AmericaMovil-Prepaid mobile-P14.09","name":"P14.09","position":9,"score":0,"value":"No Disclosure Found"},{"id":"P14-AmericaMovil-Prepaid mobile-P14.10","name":"P14.10","position":10,"score":"NA","value":"NA"},{"id":"P14-AmericaMovil-Prepaid mobile-P14.11","name":"P14.11","position":11,"score":"NA","value":"NA"}]},"Amazon":{"Amazon Cloud":[{"id":"P14-Amazon-Amazon Cloud-P14.01","name":"P14.01","position":1,"score":100,"value":"Yes"},{"id":"P14-Amazon-Amazon Cloud-P14.02","name":"P14.02","position":2,"score":50,"value":"Partial"},{"id":"P14-Amazon-Amazon Cloud-P14.03","name":"P14.03","position":3,"score":100,"value":"Yes"},{"id":"P14-Amazon-Amazon Cloud-P14.04","name":"P14.04","position":4,"score":"NA","value":"NA"},{"id":"P14-Amazon-Amazon Cloud-P14.05","name":"P14.05","position":5,"score":"NA","value":"NA"},{"id":"P14-Amazon-Amazon Cloud-P14.06","name":"P14.06","position":6,"score":"NA","value":"NA"},{"id":"P14-Amazon-Amazon Cloud-P14.07","name":"P14.07","position":7,"score":"NA","value":"NA"},{"id":"P14-Amazon-Amazon Cloud-P14.08","name":"P14.08","position":8,"score":"NA","value":"NA"},{"id":"P14-Amazon-Amazon Cloud-P14.09","name":"P14.09","position":9,"score":"NA","value":"NA"},{"id":"P14-Amazon-Amazon Cloud-P14.10","name":"P14.10","position":10,"score":"NA","value":"NA"},{"id":"P14-Amazon-Amazon Cloud-P14.11","name":"P14.11","position":11,"score":"NA","value":"NA"}],"Alexa":[{"id":"P14-Amazon-Alexa-P14.01","name":"P14.01","position":1,"score":100,"value":"Yes"},{"id":"P14-Amazon-Alexa-P14.02","name":"P14.02","position":2,"score":50,"value":"Partial"},{"id":"P14-Amazon-Alexa-P14.03","name":"P14.03","position":3,"score":100,"value":"Yes"},{"id":"P14-Amazon-Alexa-P14.04","name":"P14.04","position":4,"score":0,"value":"No Disclosure Found"},{"id":"P14-Amazon-Alexa-P14.05","name":"P14.05","position":5,"score":"NA","value":"NA"},{"id":"P14-Amazon-Alexa-P14.06","name":"P14.06","position":6,"score":"NA","value":"NA"},{"id":"P14-Amazon-Alexa-P14.07","name":"P14.07","position":7,"score":0,"value":"No Disclosure Found"},{"id":"P14-Amazon-Alexa-P14.08","name":"P14.08","position":8,"score":0,"value":"No Disclosure Found"},{"id":"P14-Amazon-Alexa-P14.09","name":"P14.09","position":9,"score":0,"value":"No Disclosure Found"},{"id":"P14-Amazon-Alexa-P14.10","name":"P14.10","position":10,"score":0,"value":"No Disclosure Found"},{"id":"P14-Amazon-Alexa-P14.11","name":"P14.11","position":11,"score":0,"value":"No Disclosure Found"}],"Amazon.com":[{"id":"P14-Amazon-Amazon.com-P14.01","name":"P14.01","position":1,"score":100,"value":"Yes"},{"id":"P14-Amazon-Amazon.com-P14.02","name":"P14.02","position":2,"score":50,"value":"Partial"},{"id":"P14-Amazon-Amazon.com-P14.03","name":"P14.03","position":3,"score":100,"value":"Yes"},{"id":"P14-Amazon-Amazon.com-P14.04","name":"P14.04","position":4,"score":"NA","value":"NA"},{"id":"P14-Amazon-Amazon.com-P14.05","name":"P14.05","position":5,"score":"NA","value":"NA"},{"id":"P14-Amazon-Amazon.com-P14.06","name":"P14.06","position":6,"score":"NA","value":"NA"},{"id":"P14-Amazon-Amazon.com-P14.07","name":"P14.07","position":7,"score":"NA","value":"NA"},{"id":"P14-Amazon-Amazon.com-P14.08","name":"P14.08","position":8,"score":"NA","value":"NA"},{"id":"P14-Amazon-Amazon.com-P14.09","name":"P14.09","position":9,"score":"NA","value":"NA"},{"id":"P14-Amazon-Amazon.com-P14.10","name":"P14.10","position":10,"score":"NA","value":"NA"},{"id":"P14-Amazon-Amazon.com-P14.11","name":"P14.11","position":11,"score":"NA","value":"NA"}]},"Alibaba":{"AliGenie":[{"id":"P14-Alibaba-AliGenie-P14.01","name":"P14.01","position":1,"score":100,"value":"Yes"},{"id":"P14-Alibaba-AliGenie-P14.02","name":"P14.02","position":2,"score":50,"value":"Partial"},{"id":"P14-Alibaba-AliGenie-P14.03","name":"P14.03","position":3,"score":0,"value":"No"},{"id":"P14-Alibaba-AliGenie-P14.04","name":"P14.04","position":4,"score":50,"value":"Partial"},{"id":"P14-Alibaba-AliGenie-P14.05","name":"P14.05","position":5,"score":"NA","value":"NA"},{"id":"P14-Alibaba-AliGenie-P14.06","name":"P14.06","position":6,"score":"NA","value":"NA"},{"id":"P14-Alibaba-AliGenie-P14.07","name":"P14.07","position":7,"score":0,"value":"No Disclosure Found"},{"id":"P14-Alibaba-AliGenie-P14.08","name":"P14.08","position":8,"score":0,"value":"No Disclosure Found"},{"id":"P14-Alibaba-AliGenie-P14.09","name":"P14.09","position":9,"score":0,"value":"No Disclosure Found"},{"id":"P14-Alibaba-AliGenie-P14.10","name":"P14.10","position":10,"score":0,"value":"No Disclosure Found"},{"id":"P14-Alibaba-AliGenie-P14.11","name":"P14.11","position":11,"score":0,"value":"No Disclosure Found"}],"Taobao.com":[{"id":"P14-Alibaba-Taobao.com-P14.01","name":"P14.01","position":1,"score":100,"value":"Yes"},{"id":"P14-Alibaba-Taobao.com-P14.02","name":"P14.02","position":2,"score":50,"value":"Partial"},{"id":"P14-Alibaba-Taobao.com-P14.03","name":"P14.03","position":3,"score":0,"value":"No"},{"id":"P14-Alibaba-Taobao.com-P14.04","name":"P14.04","position":4,"score":"NA","value":"NA"},{"id":"P14-Alibaba-Taobao.com-P14.05","name":"P14.05","position":5,"score":"NA","value":"NA"},{"id":"P14-Alibaba-Taobao.com-P14.06","name":"P14.06","position":6,"score":"NA","value":"NA"},{"id":"P14-Alibaba-Taobao.com-P14.07","name":"P14.07","position":7,"score":"NA","value":"NA"},{"id":"P14-Alibaba-Taobao.com-P14.08","name":"P14.08","position":8,"score":"NA","value":"NA"},{"id":"P14-Alibaba-Taobao.com-P14.09","name":"P14.09","position":9,"score":"NA","value":"NA"},{"id":"P14-Alibaba-Taobao.com-P14.10","name":"P14.10","position":10,"score":"NA","value":"NA"},{"id":"P14-Alibaba-Taobao.com-P14.11","name":"P14.11","position":11,"score":"NA","value":"NA"}]}}